Workbook

Sheet raw_output
A1: age_effect | B1: initial_effect | C1: final_effect | D1: mort_effect | E1: prod_effect | F1: fert_effect | G1: pop_path_diffs | H1: pop_diffs_2045_2065 | I1: pop_diffs_2026_2100 | J1: total_pop_diff_2050 | K1: avg_diff | L1: avg_gdp_pc_diff | M1: discount_rate | N1: NPV | O1: QALY 20, $B | P1: QALY NPV, $T
A2: 40 | B2: 10 | C2: 20 | D2: 0.1 | E2: 0.6 | F2: 0 | G2: 6.5547806 | H2: 23.706732 | I2: 0.26811135 | J2: 0.2681277 | K2: 339.01455 | L2: 984.17306 | M2: 0.01 | N2: 25.967443 | O2: 53.133253 | P2: 3.1176538
A3: 40 | B3: 10 | C3: 20 | D3: 0.1 | E3: 0.6 | F3: 0 | G3: 6.5547806 | H3: 23.706732 | I3: 0.26811135 | J3: 0.2681277 | K3: 339.01455 | L3: 984.17306 | M3: 0.02 | N3: 14.427577 | O3: 53.133253 | P3: 1.8208154
A4: 40 | B4: 10 | C4: 20 | D4: 0.1 | E4: 0.6 | F4: 0 | G4: 6.5547806 | H4: 23.706732 | I4: 0.26811135 | J4: 0.2681277 | K4: 339.01455 | L4: 984.17306 | M4: 0.03 | N4: 8.4961746 | O4: 53.133253 | P4: 1.1190228
A5: 40 | B5: 10 | C5: 20 | D5: 0.1 | E5: 0.6 | F5: 0 | G5: 6.5547806 | H5: 23.706732 | I5: 0.26811135 | J5: 0.2681277 | K5: 339.01455 | L5: 984.17306 | M5: 0.035 | N5: 6.6541306 | O5: 53.133253 | P5: 0.89263237
A6: 40 | B6: 10 | C6: 20 | D6: 0.1 | E6: 0.6 | F6: 0 | G6: 6.5547806 | H6: 23.706732 | I6: 0.26811135 | J6: 0.2681277 | K6: 339.01455 | L6: 984.17306 | M6: 0.04 | N6: 5.2770644 | O6: 53.133253 | P6: 0.7195986
A7: 40 | B7: 10 | C7: 20 | D7: 0.1 | E7: 0.6 | F7: 0 | G7: 6.5547806 | H7: 23.706732 | I7: 0.26811135 | J7: 0.2681277 | K7: 339.01455 | L7: 984.17306 | M7: 0.05 | N7: 3.4327845 | O7: 53.133253 | P7: 0.48118842
A8: 40 | B8: 10 | C8: 20 | D8: 0.1 | E8: 0.6 | F8: 0 | G8: 6.5547806 | H8: 23.706732 | I8: 0.26811135 | J8: 0.2681277 | K8: 339.01455 | L8: 984.17306 | M8: 0.06 | N8: 2.3204045 | O8: 53.133253 | P8: 0.33258074
A9: 40 | B9: 10 | C9: 20 | D9: 0.1 | E9: 0.35 | F9: 0 | G9: 6.5547806 | H9: 23.706732 | I9: 0.26811135 | J9: 0.2681277 | K9: 201.2899 | L9: 507.82275 | M9: 0.01 | N9: 16.132365 | O9: 53.133253 | P9: 3.1176538
A10: 40 | B10: 10 | C10: 20 | D10: 0.1 | E10: 0.35 | F10: 0 | G10: 6.5547806 | H10: 23.706732 | I10: 0.26811135 | J10: 0.2681277 | K10: 201.2899 | L10: 507.82275 | M10: 0.02 | N10: 8.9055794 | O10: 53.133253 | P10: 1.8208154
A11: 40 | B11: 10 | C11: 20 | D11: 0.1 | E11: 0.35 | F11: 0 | G11: 6.5547806 | H11: 23.706732 | I11: 0.26811135 | J11: 0.2681277 | K11: 201.2899 | L11: 507.82275 | M11: 0.03 | N11: 5.2064902 | O11: 53.133253 | P11: 1.1190228
A12: 40 | B12: 10 | C12: 20 | D12: 0.1 | E12: 0.35 | F12: 0 | G12: 6.5547806 | H12: 23.706732 | I12: 0.26811135 | J12: 0.2681277 | K12: 201.2899 | L12: 507.82275 | M12: 0.035 | N12: 4.0621892 | O12: 53.133253 | P12: 0.89263237
A13: 40 | B13: 10 | C13: 20 | D13: 0.1 | E13: 0.35 | F13: 0 | G13: 6.5547806 | H13: 23.706732 | I13: 0.26811135 | J13: 0.2681277 | K13: 201.2899 | L13: 507.82275 | M13: 0.04 | N13: 3.209096 | O13: 53.133253 | P13: 0.7195986
... A197: 65 | B197: 10 | C197: 20 | D197: 2.5 | E197: 2.5 | F197: 0.6 | G197: 135.44598 | H197: 466.93838 | I197: 5.6236576 | J197: 5.6236576 | K197: 1696.7647 | L197: 1894.7362 | M197: 0.06 | N197: 11.372369 | O197: 1095.2527 | P197: 6.7178564

Sheet Overall Output. Labeled
J1: avg_diff | K1: NPV | L1: pop_diffs_2050 | M1: avg_gdp_pc_diff | N1: discount_rate | P1: mort_effect | Q1: prod_effect | R1: fert_effect | S1: initial_effect | T1: final_effect | U1: age_effect
A2: Chapter Number | B2: Future Number | C2: Future Name | D2: Simulation Number | E2: Table Number | F2: Mortality decrease in years | G2: Productivity increase in years | H2: Fertility increase in years | I2: Ages Affected | J2: Annual change in U.S. GDP (Avg. 2045-2064) | K2: NPV of increased GDP over several decades | L2: Additional Living People in 2050 | M2: Change in GDP Per Capita | N2: Discount Rate | O2: Adherence Rate | P2: adj mort | Q2: adj prod | R2: adj fert
A3: 5 | B3: 1 | C3: Slow brain aging | D3: 1 | E3: 1 | F3: 0.2 | G3: 0.7 | H3: 0 | I3: =CONCATENATE(U3,"+") -> 40+ | J3: =IF(V3>1000,_xlfn.CONCAT(TEXT(V3/1000,"$#.0"),"T"),_xlfn.CONCAT(TEXT(V3,"$#"),"B")) -> $201B | K3: =_xlfn.CONCAT(TEXT(SUMIFS(raw_output!$N$2:$N$197,raw_output!$M$2:$M$197,'Overall Output. Labeled'!$N3,raw_output!$A$2:$A$197,'Overall Output. Labeled'!$U3,raw_output!$B$2:$B$197,'Overall Output. Labeled'!$S3,raw_output!$C$2:$C$197,'Overall Output. Labeled'!$T3,raw_output!$D$2:$D$197,'Overall Output. Labeled'!$P3,raw_output!$E$2:$E$197,'Overall Output. Labeled'!$Q3,raw_output!$F$2:$F$197,'Overall Output. Labeled'!$R3),"$#.0"),"T") -> $8.9T | L3: =IF(W3>1000,_xlfn.CONCAT(TEXT(W3/1000,"#.#"),"M"),_xlfn.CONCAT(TEXT(W3,"#"),"k")) -> 268k | M3: =TEXT(SUMIFS(raw_output!$L$2:$L$197,raw_output!$M$2:$M$197,'Overall Output. Labeled'!$N3,raw_output!$A$2:$A$197,'Overall Output. Labeled'!$U3,raw_output!$B$2:$B$197,'Overall Output. Labeled'!$S3,raw_output!$C$2:$C$197,'Overall Output. Labeled'!$T3,raw_output!$D$2:$D$197,'Overall Output. Labeled'!$P3,raw_output!$E$2:$E$197,'Overall Output. Labeled'!$Q3,raw_output!$F$2:$F$197,'Overall Output. Labeled'!$R3),"$#.##") -> $507.82 | N3: 0.02 | O3: 0.5 | P3: =F3*$O3 -> 0.1 | Q3: =G3*$O3 -> 0.35 | R3: =H3*$O3 -> 0 | S3: 10 | T3: 20 | U3: 40 | V3: =SUMIFS(raw_output!$K$2:$K$197,raw_output!$A$2:$A$197,'Overall Output. Labeled'!$U3,raw_output!$B$2:$B$197,'Overall Output. Labeled'!$S3,raw_output!$C$2:$C$197,'Overall Output. Labeled'!$T3,raw_output!$D$2:$D$197,'Overall Output. Labeled'!$P3,raw_output!$E$2:$E$197,'Overall Output. Labeled'!$Q3,raw_output!$F$2:$F$197,'Overall Output. Labeled'!$R3,raw_output!$M$2:$M$197,'Overall Output. Labeled'!$N3) -> 201.2899 | W3: =SUMIFS(raw_output!$J$2:$J$197,raw_output!$M$2:$M$197,'Overall Output. Labeled'!$N3,raw_output!$A$2:$A$197,'Overall Output. Labeled'!$U3,raw_output!$B$2:$B$197,'Overall Output. Labeled'!$S3,raw_output!$C$2:$C$197,'Overall Output. Labeled'!$T3,raw_output!$D$2:$D$197,'Overall Output. Labeled'!$P3,raw_output!$E$2:$E$197,'Overall Output. Labeled'!$Q3,raw_output!$F$2:$F$197,'Overall Output. Labeled'!$R3)*1000 -> 268.1277
A4: 6 | B4: 2 | C4: Slow reproductive aging | D4: 3 | E4: 3 | F4: 0.02 | G4: 0.1 | H4: 1 | I4: =CONCATENATE(U4,"+") -> 40+ | J4: =IF(V4>1000,_xlfn.CONCAT(TEXT(V4/1000,"$#.0"),"T"),_xlfn.CONCAT(TEXT(V4,"$#"),"B")) -> $9B | K4: =_xlfn.CONCAT(TEXT(SUMIFS(raw_output!$N$2:$N$197,raw_output!$M$2:$M$197,'Overall Output. Labeled'!$N4,raw_output!$A$2:$A$197,'Overall Output. Labeled'!$U4,raw_output!$B$2:$B$197,'Overall Output. Labeled'!$S4,raw_output!$C$2:$C$197,'Overall Output. Labeled'!$T4,raw_output!$D$2:$D$197,'Overall Output. Labeled'!$P4,raw_output!$E$2:$E$197,'Overall Output. Labeled'!$Q4,raw_output!$F$2:$F$197,'Overall Output. Labeled'!$R4),"$#.0"),"T") -> $9.3T | L4: =IF(W4>1000,_xlfn.CONCAT(TEXT(W4/1000,"#.#"),"M"),_xlfn.CONCAT(TEXT(W4,"#"),"k")) -> 391k | M4: =TEXT(SUMIFS(raw_output!$L$2:$L$197,raw_output!$M$2:$M$197,'Overall Output. Labeled'!$N4,raw_output!$A$2:$A$197,'Overall Output. Labeled'!$U4,raw_output!$B$2:$B$197,'Overall Output. Labeled'!$S4,raw_output!$C$2:$C$197,'Overall Output. Labeled'!$T4,raw_output!$D$2:$D$197,'Overall Output. Labeled'!$P4,raw_output!$E$2:$E$197,'Overall Output. Labeled'!$Q4,raw_output!$F$2:$F$197,'Overall Output. Labeled'!$R4),"$#.##") -> -$5.25 | N4: 0.02 | O4: 0.5 | P4: =F4*$O4 -> 0.01 | Q4: =G4*$O4 -> 0.05 | R4: =H4*$O4 -> 0.5 | S4: 10 | T4: 20 | U4: 40 | V4: =SUMIFS(raw_output!$K$2:$K$197,raw_output!$A$2:$A$197,'Overall Output. Labeled'!$U4,raw_output!$B$2:$B$197,'Overall Output. Labeled'!$S4,raw_output!$C$2:$C$197,'Overall Output. Labeled'!$T4,raw_output!$D$2:$D$197,'Overall Output. Labeled'!$P4,raw_output!$E$2:$E$197,'Overall Output. Labeled'!$Q4,raw_output!$F$2:$F$197,'Overall Output. Labeled'!$R4,raw_output!$M$2:$M$197,'Overall Output. Labeled'!$N4) -> 9.0672976 | W4: {=SUMIFS(raw_output!$J$2:$J$197,raw_output!$M$2:$M$197,'Overall Output. Labeled'!$N4,raw_output!$A$2:$A$197,'Overall Output. Labeled'!$U4,raw_output!$B$2:$B$197,'Overall Output. Labeled'!$S4,raw_output!$C$2:$C$197,'Overall Output. Labeled'!$T4,raw_output!$D$2:$D$197,'Overall Output. Labeled'!$P4,raw_output!$E$2:$E$197,'Overall Output. Labeled'!$Q4,raw_output!$F$2:$F$197,'Overall Output. Labeled'!$R4)*1000} -> 391.36761
A5: 7 | B5: 3 | C5: Replacing aging, 4x | D5: 4 | E5: 4 | F5: 0.44 | G5: 0 | H5: 0 | I5: =CONCATENATE(U5,"+") -> 40+ | J5: =IF(V5>1000,_xlfn.CONCAT(TEXT(V5/1000,"$#.0"),"T"),_xlfn.CONCAT(TEXT(V5,"$#"),"B")) -> $118B | K5: =_xlfn.CONCAT(TEXT(SUMIFS(raw_output!$N$2:$N$197,raw_output!$M$2:$M$197,'Overall Output. Labeled'!$N5,raw_output!$A$2:$A$197,'Overall Output. Labeled'!$U5,raw_output!$B$2:$B$197,'Overall Output. Labeled'!$S5,raw_output!$C$2:$C$197,'Overall Output. Labeled'!$T5,raw_output!$D$2:$D$197,'Overall Output. Labeled'!$P5,raw_output!$E$2:$E$197,'Overall Output. Labeled'!$Q5,raw_output!$F$2:$F$197,'Overall Output. Labeled'!$R5),"$#.0"),"T") -> $6.8T | L5: =IF(W5>1000,_xlfn.CONCAT(TEXT(W5/1000,"#.#"),"M"),_xlfn.CONCAT(TEXT(W5,"#"),"k")) -> 1.2M | M5: =TEXT(SUMIFS(raw_output!$L$2:$L$197,raw_output!$M$2:$M$197,'Overall Output. Labeled'!$N5,raw_output!$A$2:$A$197,'Overall Output. Labeled'!$U5,raw_output!$B$2:$B$197,'Overall Output. Labeled'!$S5,raw_output!$C$2:$C$197,'Overall Output. Labeled'!$T5,raw_output!$D$2:$D$197,'Overall Output. Labeled'!$P5,raw_output!$E$2:$E$197,'Overall Output. Labeled'!$Q5,raw_output!$F$2:$F$197,'Overall Output. Labeled'!$R5),"$#.##") -> -$436.88 | N5: 0.02 | O5: 1 | P5: =F5*$O5 -> 0.44 | Q5: =G5*$O5 -> 0 | R5: =H5*$O5 -> 0 | S5: 10 | T5: 20 | U5: 40 | V5: =SUMIFS(raw_output!$K$2:$K$197,raw_output!$A$2:$A$197,'Overall Output. Labeled'!$U5,raw_output!$B$2:$B$197,'Overall Output. Labeled'!$S5,raw_output!$C$2:$C$197,'Overall Output. Labeled'!$T5,raw_output!$D$2:$D$197,'Overall Output. Labeled'!$P5,raw_output!$E$2:$E$197,'Overall Output. Labeled'!$Q5,raw_output!$F$2:$F$197,'Overall Output. Labeled'!$R5,raw_output!$M$2:$M$197,'Overall Output. Labeled'!$N5) -> 118.19972 | W5: {=SUMIFS(raw_output!$J$2:$J$197,raw_output!$M$2:$M$197,'Overall Output. Labeled'!$N5,raw_output!$A$2:$A$197,'Overall Output. Labeled'!$U5,raw_output!$B$2:$B$197,'Overall Output. Labeled'!$S5,raw_output!$C$2:$C$197,'Overall Output. Labeled'!$T5,raw_output!$D$2:$D$197,'Overall Output. Labeled'!$P5,raw_output!$E$2:$E$197,'Overall Output. Labeled'!$Q5,raw_output!$F$2:$F$197,'Overall Output. Labeled'!$R5)*1000} -> 1193.1255
A6: 7 | B6: 3 | C6: Replacing aging, 2x | D6: 4 | E6: 4 | F6: 0.22 | G6: 0 | H6: 0 | I6: =CONCATENATE(U6,"+") -> 40+ | J6: =IF(V6>1000,_xlfn.CONCAT(TEXT(V6/1000,"$#.0"),"T"),_xlfn.CONCAT(TEXT(V6,"$#"),"B")) -> $50B | K6: =_xlfn.CONCAT(TEXT(SUMIFS(raw_output!$N$2:$N$197,raw_output!$M$2:$M$197,'Overall Output. Labeled'!$N6,raw_output!$A$2:$A$197,'Overall Output. Labeled'!$U6,raw_output!$B$2:$B$197,'Overall Output. Labeled'!$S6,raw_output!$C$2:$C$197,'Overall Output. Labeled'!$T6,raw_output!$D$2:$D$197,'Overall Output. Labeled'!$P6,raw_output!$E$2:$E$197,'Overall Output. Labeled'!$Q6,raw_output!$F$2:$F$197,'Overall Output. Labeled'!$R6),"$#.0"),"T") -> $3.2T | L6: =IF(W6>1000,_xlfn.CONCAT(TEXT(W6/1000,"#.#"),"M"),_xlfn.CONCAT(TEXT(W6,"#"),"k")) -> 592k | M6: =TEXT(SUMIFS(raw_output!$L$2:$L$197,raw_output!$M$2:$M$197,'Overall Output. Labeled'!$N6,raw_output!$A$2:$A$197,'Overall Output. Labeled'!$U6,raw_output!$B$2:$B$197,'Overall Output. Labeled'!$S6,raw_output!$C$2:$C$197,'Overall Output. Labeled'!$T6,raw_output!$D$2:$D$197,'Overall Output. Labeled'!$P6,raw_output!$E$2:$E$197,'Overall Output. Labeled'!$Q6,raw_output!$F$2:$F$197,'Overall Output. Labeled'!$R6),"$#.##") -> -$247.15 | N6: 0.02 | O6: 1 | P6: =F6*$O6 -> 0.22 | Q6: =G6*$O6 -> 0 | R6: =H6*$O6 -> 0 | S6: 10 | T6: 20 | U6: 40 | V6: =SUMIFS(raw_output!$K$2:$K$197,raw_output!$A$2:$A$197,'Overall Output. Labeled'!$U6,raw_output!$B$2:$B$197,'Overall Output. Labeled'!$S6,raw_output!$C$2:$C$197,'Overall Output. Labeled'!$T6,raw_output!$D$2:$D$197,'Overall Output. Labeled'!$P6,raw_output!$E$2:$E$197,'Overall Output. Labeled'!$Q6,raw_output!$F$2:$F$197,'Overall Output. Labeled'!$R6,raw_output!$M$2:$M$197,'Overall Output. Labeled'!$N6) -> 49.515117 | W6: {=SUMIFS(raw_output!$J$2:$J$197,raw_output!$M$2:$M$197,'Overall Output. Labeled'!$N6,raw_output!$A$2:$A$197,'Overall Output. Labeled'!$U6,raw_output!$B$2:$B$197,'Overall Output. Labeled'!$S6,raw_output!$C$2:$C$197,'Overall Output. Labeled'!$T6,raw_output!$D$2:$D$197,'Overall Output. Labeled'!$P6,raw_output!$E$2:$E$197,'Overall Output. Labeled'!$Q6,raw_output!$F$2:$F$197,'Overall Output. Labeled'!$R6)*1000} -> 592.2211
A7: 8 | B7: 4 | C7: 1st gen | D7: ? | F7: 0.82 | G7: 0.727 | H7: 0 | I7: =CONCATENATE(U7,"+") -> 65+ | J7: =IF(V7>1000,_xlfn.CONCAT(TEXT(V7/1000,"$#.0"),"T"),_xlfn.CONCAT(TEXT(V7,"$#"),"B")) -> $40B | K7: =_xlfn.CONCAT(TEXT(SUMIFS(raw_output!$N$2:$N$197,raw_output!$M$2:$M$197,'Overall Output. Labeled'!$N7,raw_output!$A$2:$A$197,'Overall Output. Labeled'!$U7,raw_output!$B$2:$B$197,'Overall Output. Labeled'!$S7,raw_output!$C$2:$C$197,'Overall Output. Labeled'!$T7,raw_output!$D$2:$D$197,'Overall Output. Labeled'!$P7,raw_output!$E$2:$E$197,'Overall Output. Labeled'!$Q7,raw_output!$F$2:$F$197,'Overall Output. Labeled'!$R7),"$#.0"),"T") -> $2.4T | L7: =IF(W7>1000,_xlfn.CONCAT(TEXT(W7/1000,"#.#"),"M"),_xlfn.CONCAT(TEXT(W7,"#"),"k")) -> 275k | M7: =TEXT(SUMIFS(raw_output!$L$2:$L$197,raw_output!$M$2:$M$197,'Overall Output. Labeled'!$N7,raw_output!$A$2:$A$197,'Overall Output. Labeled'!$U7,raw_output!$B$2:$B$197,'Overall Output. Labeled'!$S7,raw_output!$C$2:$C$197,'Overall Output. Labeled'!$T7,raw_output!$D$2:$D$197,'Overall Output. Labeled'!$P7,raw_output!$E$2:$E$197,'Overall Output. Labeled'!$Q7,raw_output!$F$2:$F$197,'Overall Output. Labeled'!$R7),"$#.##") -> -$19.85 | N7: 0.02 | O7: 0.11 | P7: 0.09 | Q7: 0.08 | R7: =H7*$O7 -> 0 | S7: 5 | T7: 10 | U7: 65 | V7: =SUMIFS(raw_output!$K$2:$K$197,raw_output!$A$2:$A$197,'Overall Output. Labeled'!$U7,raw_output!$B$2:$B$197,'Overall Output. Labeled'!$S7,raw_output!$C$2:$C$197,'Overall Output. Labeled'!$T7,raw_output!$D$2:$D$197,'Overall Output. Labeled'!$P7,raw_output!$E$2:$E$197,'Overall Output. Labeled'!$Q7,raw_output!$F$2:$F$197,'Overall Output. Labeled'!$R7,raw_output!$M$2:$M$197,'Overall Output. Labeled'!$N7) -> 40.442704 | W7: {=SUMIFS(raw_output!$J$2:$J$197,raw_output!$M$2:$M$197,'Overall Output. Labeled'!$N7,raw_output!$A$2:$A$197,'Overall Output. Labeled'!$U7,raw_output!$B$2:$B$197,'Overall Output. Labeled'!$S7,raw_output!$C$2:$C$197,'Overall Output. Labeled'!$T7,raw_output!$D$2:$D$197,'Overall Output. Labeled'!$P7,raw_output!$E$2:$E$197,'Overall Output. Labeled'!$Q7,raw_output!$F$2:$F$197,'Overall Output. Labeled'!$R7)*1000} -> 275.20844
C8: 1st gen, broader population | F8: 0.81 | G8: 0.72 | H8: 0 | I8: =CONCATENATE(U8,"+") -> 65+ | J8: =IF(V8>1000,_xlfn.CONCAT(TEXT(V8/1000,"$#.0"),"T"),_xlfn.CONCAT(TEXT(V8,"$#"),"B")) -> $79B | K8: =_xlfn.CONCAT(TEXT(SUMIFS(raw_output!$N$2:$N$197,raw_output!$M$2:$M$197,'Overall Output. Labeled'!$N8,raw_output!$A$2:$A$197,'Overall Output. Labeled'!$U8,raw_output!$B$2:$B$197,'Overall Output. Labeled'!$S8,raw_output!$C$2:$C$197,'Overall Output. Labeled'!$T8,raw_output!$D$2:$D$197,'Overall Output. Labeled'!$P8,raw_output!$E$2:$E$197,'Overall Output. Labeled'!$Q8,raw_output!$F$2:$F$197,'Overall Output. Labeled'!$R8),"$#.0"),"T") -> $4.2T | L8: =IF(W8>1000,_xlfn.CONCAT(TEXT(W8/1000,"#.#"),"M"),_xlfn.CONCAT(TEXT(W8,"#"),"k")) -> 460k | M8: =TEXT(SUMIFS(raw_output!$L$2:$L$197,raw_output!$M$2:$M$197,'Overall Output. Labeled'!$N8,raw_output!$A$2:$A$197,'Overall Output. Labeled'!$U8,raw_output!$B$2:$B$197,'Overall Output. Labeled'!$S8,raw_output!$C$2:$C$197,'Overall Output. Labeled'!$T8,raw_output!$D$2:$D$197,'Overall Output. Labeled'!$P8,raw_output!$E$2:$E$197,'Overall Output. Labeled'!$Q8,raw_output!$F$2:$F$197,'Overall Output. Labeled'!$R8),"$#.##") -> $3.94 | N8: 0.02 | O8: 0.185 | P8: 0.15 | Q8: 0.13 | R8: 0 | S8: 5 | T8: 10 | U8: 65 | V8: =SUMIFS(raw_output!$K$2:$K$197,raw_output!$A$2:$A$197,'Overall Output. Labeled'!$U8,raw_output!$B$2:$B$197,'Overall Output. Labeled'!$S8,raw_output!$C$2:$C$197,'Overall Output. Labeled'!$T8,raw_output!$D$2:$D$197,'Overall Output. Labeled'!$P8,raw_output!$E$2:$E$197,'Overall Output. Labeled'!$Q8,raw_output!$F$2:$F$197,'Overall Output. Labeled'!$R8,raw_output!$M$2:$M$197,'Overall Output. Labeled'!$N8) -> 78.713204 | W8: {=SUMIFS(raw_output!$J$2:$J$197,raw_output!$M$2:$M$197,'Overall Output. Labeled'!$N8,raw_output!$A$2:$A$197,'Overall Output. Labeled'!$U8,raw_output!$B$2:$B$197,'Overall Output. Labeled'!$S8,raw_output!$C$2:$C$197,'Overall Output. Labeled'!$T8,raw_output!$D$2:$D$197,'Overall Output. Labeled'!$P8,raw_output!$E$2:$E$197,'Overall Output. Labeled'!$Q8,raw_output!$F$2:$F$197,'Overall Output. Labeled'!$R8)*1000} -> 460.1928
A9: 8 | B9: 4 | C9: 2nd gen | D9: ? | E9: ? | F9: 0.82 | G9: 1.44 | I9: =CONCATENATE(U9,"+") -> 40+ | J9: =IF(V9>1000,_xlfn.CONCAT(TEXT(V9/1000,"$#.0"),"T"),_xlfn.CONCAT(TEXT(V9,"$#"),"B")) -> $505B | K9: =_xlfn.CONCAT(TEXT(SUMIFS(raw_output!$N$2:$N$197,raw_output!$M$2:$M$197,'Overall Output. Labeled'!$N9,raw_output!$A$2:$A$197,'Overall Output. Labeled'!$U9,raw_output!$B$2:$B$197,'Overall Output. Labeled'!$S9,raw_output!$C$2:$C$197,'Overall Output. Labeled'!$T9,raw_output!$D$2:$D$197,'Overall Output. Labeled'!$P9,raw_output!$E$2:$E$197,'Overall Output. Labeled'!$Q9,raw_output!$F$2:$F$197,'Overall Output. Labeled'!$R9),"$#.0"),"T") -> $22.2T | L9: =IF(W9>1000,_xlfn.CONCAT(TEXT(W9/1000,"#.#"),"M"),_xlfn.CONCAT(TEXT(W9,"#"),"k")) -> 1.1M | M9: =TEXT(SUMIFS(raw_output!$L$2:$L$197,raw_output!$M$2:$M$197,'Overall Output. Labeled'!$N9,raw_output!$A$2:$A$197,'Overall Output. Labeled'!$U9,raw_output!$B$2:$B$197,'Overall Output. Labeled'!$S9,raw_output!$C$2:$C$197,'Overall Output. Labeled'!$T9,raw_output!$D$2:$D$197,'Overall Output. Labeled'!$P9,raw_output!$E$2:$E$197,'Overall Output. Labeled'!$Q9,raw_output!$F$2:$F$197,'Overall Output. Labeled'!$R9),"$#.##") -> $954.97 | N9: 0.02 | O9: 0.5 | P9: =F9*$O9 -> 0.41 | Q9: =G9*$O9 -> 0.72 | R9: =H9*$O9 -> 0 | S9: 10 | T9: 20 | U9: 40 | V9: =SUMIFS(raw_output!$K$2:$K$197,raw_output!$A$2:$A$197,'Overall Output. Labeled'!$U9,raw_output!$B$2:$B$197,'Overall Output. Labeled'!$S9,raw_output!$C$2:$C$197,'Overall Output. Labeled'!$T9,raw_output!$D$2:$D$197,'Overall Output. Labeled'!$P9,raw_output!$E$2:$E$197,'Overall Output. Labeled'!$Q9,raw_output!$F$2:$F$197,'Overall Output. Labeled'!$R9,raw_output!$M$2:$M$197,'Overall Output. Labeled'!$N9) -> 505.03884 | W9: {=SUMIFS(raw_output!$J$2:$J$197,raw_output!$M$2:$M$197,'Overall Output. Labeled'!$N9,raw_output!$A$2:$A$197,'Overall Output. Labeled'!$U9,raw_output!$B$2:$B$197,'Overall Output. Labeled'!$S9,raw_output!$C$2:$C$197,'Overall Output. Labeled'!$T9,raw_output!$D$2:$D$197,'Overall Output. Labeled'!$P9,raw_output!$E$2:$E$197,'Overall Output. Labeled'!$Q9,raw_output!$F$2:$F$197,'Overall Output. Labeled'!$R9)*1000} -> 1110.6654
C10: Delta, 2nd gen - 1st gen | J10: =IF(V10>1000,_xlfn.CONCAT(TEXT(V10/1000,"$#.0"),"T"),_xlfn.CONCAT(TEXT(V10,"$#"),"B")) -> $426B | K10: $36.2T | L10: =IF(W10>1000,_xlfn.CONCAT(TEXT(W10/1000,"#.#"),"M"),_xlfn.CONCAT(TEXT(W10,"#"),"k")) -> 650k | V10: =V9-V8 -> 426.32563 | W10: =W9-W8 -> 650.47256
A11: 8 | B11: 4 | C11: 2nd gen + OOC | D11: ? | E11: ? | F11: 0.82 | G11: 1.44 | I11: =CONCATENATE(U11,"+") -> 40+ | J11: =IF(V11>1000,_xlfn.CONCAT(TEXT(V11/1000,"$#.0"),"T"),_xlfn.CONCAT(TEXT(V11,"$#"),"B")) -> $523B | K11: =_xlfn.CONCAT(TEXT(SUMIFS(raw_output!$N$2:$N$197,raw_output!$M$2:$M$197,'Overall Output. Labeled'!$N11,raw_output!$A$2:$A$197,'Overall Output. Labeled'!$U11,raw_output!$B$2:$B$197,'Overall Output. Labeled'!$S11,raw_output!$C$2:$C$197,'Overall Output. Labeled'!$T11,raw_output!$D$2:$D$197,'Overall Output. Labeled'!$P11,raw_output!$E$2:$E$197,'Overall Output. Labeled'!$Q11,raw_output!$F$2:$F$197,'Overall Output. Labeled'!$R11),"$#.0"),"T") -> $23.3T | L11: =IF(W11>1000,_xlfn.CONCAT(TEXT(W11/1000,"#.#"),"M"),_xlfn.CONCAT(TEXT(W11,"#"),"k")) -> 1.3M | M11: =TEXT(SUMIFS(raw_output!$L$2:$L$197,raw_output!$M$2:$M$197,'Overall Output. Labeled'!$N11,raw_output!$A$2:$A$197,'Overall Output. Labeled'!$U11,raw_output!$B$2:$B$197,'Overall Output. Labeled'!$S11,raw_output!$C$2:$C$197,'Overall Output. Labeled'!$T11,raw_output!$D$2:$D$197,'Overall Output. Labeled'!$P11,raw_output!$E$2:$E$197,'Overall Output. Labeled'!$Q11,raw_output!$F$2:$F$197,'Overall Output. Labeled'!$R11),"$#.##") -> $936.43 | N11: 0.02 | O11: 0.5 | P11: =F11*$O11 -> 0.41 | Q11: =G11*$O11 -> 0.72 | R11: =H11*$O11 -> 0 | S11: 8 | T11: 16 | U11: 40 | V11: =SUMIFS(raw_output!$K$2:$K$197,raw_output!$A$2:$A$197,'Overall Output. Labeled'!$U11,raw_output!$B$2:$B$197,'Overall Output. Labeled'!$S11,raw_output!$C$2:$C$197,'Overall Output. Labeled'!$T11,raw_output!$D$2:$D$197,'Overall Output. Labeled'!$P11,raw_output!$E$2:$E$197,'Overall Output. Labeled'!$Q11,raw_output!$F$2:$F$197,'Overall Output. Labeled'!$R11,raw_output!$M$2:$M$197,'Overall Output. Labeled'!$N11) -> 522.61023 | W11: {=SUMIFS(raw_output!$J$2:$J$197,raw_output!$M$2:$M$197,'Overall Output. Labeled'!$N11,raw_output!$A$2:$A$197,'Overall Output. Labeled'!$U11,raw_output!$B$2:$B$197,'Overall Output. Labeled'!$S11,raw_output!$C$2:$C$197,'Overall Output. Labeled'!$T11,raw_output!$D$2:$D$197,'Overall Output. Labeled'!$P11,raw_output!$E$2:$E$197,'Overall Output. Labeled'!$Q11,raw_output!$F$2:$F$197,'Overall Output. Labeled'!$R11)*1000} -> 1331.7213
C12: Delta, 2nd gen OOC - 2nd gen | J12: $18B | K12: $2.0T | L12: =IF(W12>1000,_xlfn.CONCAT(TEXT(W12/1000,"#.#"),"M"),_xlfn.CONCAT(TEXT(W12,"#"),"k")) -> 221k | V12: =V11-V9 -> 17.57139 | W12: =W11-W9 -> 221.05593
A13: 9 | B13: 5 | C13: 41 the new 40 | D13: 5 | E13: ? | F13: 1 | G13: 1 | H13: 1 | I13: =CONCATENATE(U13,"+") -> 40+ | J13: =IF(V13>1000,_xlfn.CONCAT(TEXT(V13/1000,"$#.0"),"T"),_xlfn.CONCAT(TEXT(V13,"$#"),"B")) -> $408B | K13: =_xlfn.CONCAT(TEXT(SUMIFS(raw_output!$N$2:$N$197,raw_output!$M$2:$M$197,'Overall Output. Labeled'!$N13,raw_output!$A$2:$A$197,'Overall Output. Labeled'!$U13,raw_output!$B$2:$B$197,'Overall Output. Labeled'!$S13,raw_output!$C$2:$C$197,'Overall Output. Labeled'!$T13,raw_output!$D$2:$D$197,'Overall Output. Labeled'!$P13,raw_output!$E$2:$E$197,'Overall Output. Labeled'!$Q13,raw_output!$F$2:$F$197,'Overall Output. Labeled'!$R13),"$#.0"),"T") -> $27.1T | L13: =IF(W13>1000,_xlfn.CONCAT(TEXT(W13/1000,"#.#"),"M"),_xlfn.CONCAT(TEXT(W13,"#"),"k")) -> 1.7M | M13: =TEXT(SUMIFS(raw_output!$L$2:$L$197,raw_output!$M$2:$M$197,'Overall Output. Labeled'!$N13,raw_output!$A$2:$A$197,'Overall Output. Labeled'!$U13,raw_output!$B$2:$B$197,'Overall Output. Labeled'!$S13,raw_output!$C$2:$C$197,'Overall Output. Labeled'!$T13,raw_output!$D$2:$D$197,'Overall Output. Labeled'!$P13,raw_output!$E$2:$E$197,'Overall Output. Labeled'!$Q13,raw_output!$F$2:$F$197,'Overall Output. Labeled'!$R13),"$#.##") -> $425.39 | N13: 0.02 | O13: 0.5 | P13: =F13*$O13 -> 0.5 | Q13: =G13*$O13 -> 0.5 | R13: =H13*$O13 -> 0.5 | S13: 10 | T13: 20 | U13: 40 | V13: =SUMIFS(raw_output!$K$2:$K$197,raw_output!$A$2:$A$197,'Overall Output. Labeled'!$U13,raw_output!$B$2:$B$197,'Overall Output. Labeled'!$S13,raw_output!$C$2:$C$197,'Overall Output. Labeled'!$T13,raw_output!$D$2:$D$197,'Overall Output. Labeled'!$P13,raw_output!$E$2:$E$197,'Overall Output. Labeled'!$Q13,raw_output!$F$2:$F$197,'Overall Output. Labeled'!$R13,raw_output!$M$2:$M$197,'Overall Output. Labeled'!$N13) -> 408.38262 | W13: {=SUMIFS(raw_output!$J$2:$J$197,raw_output!$M$2:$M$197,'Overall Output. Labeled'!$N13,raw_output!$A$2:$A$197,'Overall Output. Labeled'!$U13,raw_output!$B$2:$B$197,'Overall Output. Labeled'!$S13,raw_output!$C$2:$C$197,'Overall Output. Labeled'!$T13,raw_output!$D$2:$D$197,'Overall Output. Labeled'!$P13,raw_output!$E$2:$E$197,'Overall Output. Labeled'!$Q13,raw_output!$F$2:$F$197,'Overall Output. Labeled'!$R13)*1000} -> 1723.1995
A14: 9 | B14: 5 | C14: 41 the new 40 | D14: 5+ | E14: ? | F14: 1 | G14: 1 | H14: 1 | I14: =CONCATENATE(U14,"+") -> 65+ | J14: =IF(V14>1000,_xlfn.CONCAT(TEXT(V14/1000,"$#.0"),"T"),_xlfn.CONCAT(TEXT(V14,"$#"),"B")) -> $326B | K14: =_xlfn.CONCAT(TEXT(SUMIFS(raw_output!$N$2:$N$197,raw_output!$M$2:$M$197,'Overall Output. Labeled'!$N14,raw_output!$A$2:$A$197,'Overall Output. Labeled'!$U14,raw_output!$B$2:$B$197,'Overall Output. Labeled'!$S14,raw_output!$C$2:$C$197,'Overall Output. Labeled'!$T14,raw_output!$D$2:$D$197,'Overall Output. Labeled'!$P14,raw_output!$E$2:$E$197,'Overall Output. Labeled'!$Q14,raw_output!$F$2:$F$197,'Overall Output. Labeled'!$R14),"$#.0"),"T") -> $14.3T | L14: =IF(W14>1000,_xlfn.CONCAT(TEXT(W14/1000,"#.#"),"M"),_xlfn.CONCAT(TEXT(W14,"#"),"k")) -> 1.2M | M14: =TEXT(SUMIFS(raw_output!$L$2:$L$197,raw_output!$M$2:$M$197,'Overall Output. Labeled'!$N14,raw_output!$A$2:$A$197,'Overall Output. Labeled'!$U14,raw_output!$B$2:$B$197,'Overall Output. Labeled'!$S14,raw_output!$C$2:$C$197,'Overall Output. Labeled'!$T14,raw_output!$D$2:$D$197,'Overall Output. Labeled'!$P14,raw_output!$E$2:$E$197,'Overall Output. Labeled'!$Q14,raw_output!$F$2:$F$197,'Overall Output. Labeled'!$R14),"$#.##") -> $327.93 | N14: 0.02 | O14: 0.5 | P14: =F14*$O14 -> 0.5 | Q14: =G14*$O14 -> 0.5 | R14: =H14*$O14 -> 0.5 | S14: 10 | T14: 20 | U14: 65 | V14: =SUMIFS(raw_output!$K$2:$K$197,raw_output!$A$2:$A$197,'Overall Output. Labeled'!$U14,raw_output!$B$2:$B$197,'Overall Output. Labeled'!$S14,raw_output!$C$2:$C$197,'Overall Output. Labeled'!$T14,raw_output!$D$2:$D$197,'Overall Output. Labeled'!$P14,raw_output!$E$2:$E$197,'Overall Output. Labeled'!$Q14,raw_output!$F$2:$F$197,'Overall Output. Labeled'!$R14,raw_output!$M$2:$M$197,'Overall Output. Labeled'!$N14) -> 326.36233 | W14: {=SUMIFS(raw_output!$J$2:$J$197,raw_output!$M$2:$M$197,'Overall Output. Labeled'!$N14,raw_output!$A$2:$A$197,'Overall Output. Labeled'!$U14,raw_output!$B$2:$B$197,'Overall Output. Labeled'!$S14,raw_output!$C$2:$C$197,'Overall Output. Labeled'!$T14,raw_output!$D$2:$D$197,'Overall Output. Labeled'!$P14,raw_output!$E$2:$E$197,'Overall Output. Labeled'!$Q14,raw_output!$F$2:$F$197,'Overall Output. Labeled'!$R14)*1000} -> 1178.3827
A15: 9 | B15: 5 | C15: 45 the new 40 | D15: 5+ | E15: ? | F15: 5 | G15: 5 | H15: 5 | I15: =CONCATENATE(U15,"+") -> 40+ | J15: =IF(V15>1000,_xlfn.CONCAT(TEXT(V15/1000,"$#.0"),"T"),_xlfn.CONCAT(TEXT(V15,"$#"),"B")) -> $2.0T | K15: =_xlfn.CONCAT(TEXT(SUMIFS(raw_output!$N$2:$N$197,raw_output!$M$2:$M$197,'Overall Output. Labeled'!$N15,raw_output!$A$2:$A$197,'Overall Output. Labeled'!$U15,raw_output!$B$2:$B$197,'Overall Output. Labeled'!$S15,raw_output!$C$2:$C$197,'Overall Output. Labeled'!$T15,raw_output!$D$2:$D$197,'Overall Output. Labeled'!$P15,raw_output!$E$2:$E$197,'Overall Output. Labeled'!$Q15,raw_output!$F$2:$F$197,'Overall Output. Labeled'!$R15),"$#.0"),"T") -> $101.9T | L15: =IF(W15>1000,_xlfn.CONCAT(TEXT(W15/1000,"#.#"),"M"),_xlfn.CONCAT(TEXT(W15,"#"),"k")) -> 6.9M | M15: =TEXT(SUMIFS(raw_output!$L$2:$L$197,raw_output!$M$2:$M$197,'Overall Output. Labeled'!$N15,raw_output!$A$2:$A$197,'Overall Output. Labeled'!$U15,raw_output!$B$2:$B$197,'Overall Output. Labeled'!$S15,raw_output!$C$2:$C$197,'Overall Output. Labeled'!$T15,raw_output!$D$2:$D$197,'Overall Output. Labeled'!$P15,raw_output!$E$2:$E$197,'Overall Output. Labeled'!$Q15,raw_output!$F$2:$F$197,'Overall Output. Labeled'!$R15),"$#.##") -> $2211.12 | N15: 0.02 | O15: 0.5 | P15: =F15*$O15 -> 2.5 | Q15: =G15*$O15 -> 2.5 | R15: 0.6 | S15: 10 | T15: 20 | U15: 40 | V15: =SUMIFS(raw_output!$K$2:$K$197,raw_output!$A$2:$A$197,'Overall Output. Labeled'!$U15,raw_output!$B$2:$B$197,'Overall Output. Labeled'!$S15,raw_output!$C$2:$C$197,'Overall Output. Labeled'!$T15,raw_output!$D$2:$D$197,'Overall Output. Labeled'!$P15,raw_output!$E$2:$E$197,'Overall Output. Labeled'!$Q15,raw_output!$F$2:$F$197,'Overall Output. Labeled'!$R15,raw_output!$M$2:$M$197,'Overall Output. Labeled'!$N15) -> 2027.9728 | W15: {=SUMIFS(raw_output!$J$2:$J$197,raw_output!$M$2:$M$197,'Overall Output. Labeled'!$N15,raw_output!$A$2:$A$197,'Overall Output. Labeled'!$U15,raw_output!$B$2:$B$197,'Overall Output. Labeled'!$S15,raw_output!$C$2:$C$197,'Overall Output. Labeled'!$T15,raw_output!$D$2:$D$197,'Overall Output. Labeled'!$P15,raw_output!$E$2:$E$197,'Overall Output. Labeled'!$Q15,raw_output!$F$2:$F$197,'Overall Output. Labeled'!$R15)*1000} -> 6911.1497
A16: 9 | B16: 5 | C16: 45 the new 40 | D16: 5+ | E16: ? | F16: 5 | G16: 5 | H16: 5 | I16: =CONCATENATE(U16,"+") -> 65+ | J16: =IF(V16>1000,_xlfn.CONCAT(TEXT(V16/1000,"$#.0"),"T"),_xlfn.CONCAT(TEXT(V16,"$#"),"B")) -> $1.7T | K16: =_xlfn.CONCAT(TEXT(SUMIFS(raw_output!$N$2:$N$197,raw_output!$M$2:$M$197,'Overall Output. Labeled'!$N16,raw_output!$A$2:$A$197,'Overall Output. Labeled'!$U16,raw_output!$B$2:$B$197,'Overall Output. Labeled'!$S16,raw_output!$C$2:$C$197,'Overall Output. Labeled'!$T16,raw_output!$D$2:$D$197,'Overall Output. Labeled'!$P16,raw_output!$E$2:$E$197,'Overall Output. Labeled'!$Q16,raw_output!$F$2:$F$197,'Overall Output. Labeled'!$R16),"$#.0"),"T") -> $72.8T | L16: =IF(W16>1000,_xlfn.CONCAT(TEXT(W16/1000,"#.#"),"M"),_xlfn.CONCAT(TEXT(W16,"#"),"k")) -> 5.6M | M16: =TEXT(SUMIFS(raw_output!$L$2:$L$197,raw_output!$M$2:$M$197,'Overall Output. Labeled'!$N16,raw_output!$A$2:$A$197,'Overall Output. Labeled'!$U16,raw_output!$B$2:$B$197,'Overall Output. Labeled'!$S16,raw_output!$C$2:$C$197,'Overall Output. Labeled'!$T16,raw_output!$D$2:$D$197,'Overall Output. Labeled'!$P16,raw_output!$E$2:$E$197,'Overall Output. Labeled'!$Q16,raw_output!$F$2:$F$197,'Overall Output. Labeled'!$R16),"$#.##") -> $1894.74 | N16: 0.02 | O16: 0.5 | P16: =F16*$O16 -> 2.5 | Q16: =G16*$O16 -> 2.5 | R16: 0.6 | S16: 10 | T16: 20 | U16: 65 | V16: =SUMIFS(raw_output!$K$2:$K$197,raw_output!$A$2:$A$197,'Overall Output. Labeled'!$U16,raw_output!$B$2:$B$197,'Overall Output. Labeled'!$S16,raw_output!$C$2:$C$197,'Overall Output. Labeled'!$T16,raw_output!$D$2:$D$197,'Overall Output. Labeled'!$P16,raw_output!$E$2:$E$197,'Overall Output. Labeled'!$Q16,raw_output!$F$2:$F$197,'Overall Output. Labeled'!$R16,raw_output!$M$2:$M$197,'Overall Output. Labeled'!$N16) -> 1696.7647 | W16: {=SUMIFS(raw_output!$J$2:$J$197,raw_output!$M$2:$M$197,'Overall Output. Labeled'!$N16,raw_output!$A$2:$A$197,'Overall Output. Labeled'!$U16,raw_output!$B$2:$B$197,'Overall Output. Labeled'!$S16,raw_output!$C$2:$C$197,'Overall Output. Labeled'!$T16,raw_output!$D$2:$D$197,'Overall Output. Labeled'!$P16,raw_output!$E$2:$E$197,'Overall Output. Labeled'!$Q16,raw_output!$F$2:$F$197,'Overall Output. Labeled'!$R16)*1000} -> 5623.6576
A17: 11 | B17: NA | C17: Curing all cancers | E17: ? | F17: ? | G17: 0 | H17: 0 | I17: =CONCATENATE(U17,"+") -> 40+ | K17: $80T | N17: 0.035 | S17: 10 | T17: 20 | U17: 40 | V17: =SUMIFS(raw_output!$K$2:$K$197,raw_output!$A$2:$A$197,'Overall Output. Labeled'!$U17,raw_output!$B$2:$B$197,'Overall Output. Labeled'!$S17,raw_output!$C$2:$C$197,'Overall Output. Labeled'!$T17,raw_output!$D$2:$D$197,'Overall Output. Labeled'!$P17,raw_output!$E$2:$E$197,'Overall Output. Labeled'!$Q17,raw_output!$F$2:$F$197,'Overall Output. Labeled'!$R17,raw_output!$M$2:$M$197,'Overall Output. Labeled'!$N17) -> 0
A18: 11 | B18: NA | C18: 45 the new 40, 100% adhere | D18: 5+ | E18: ? | F18: 5 | G18: 5 | H18: 5 | I18: =CONCATENATE(U18,"+") -> 40+ | J18: =IF(V18>1000,_xlfn.CONCAT(TEXT(V18/1000,"$#.0"),"T"),_xlfn.CONCAT(TEXT(V18,"$#"),"B")) -> $4.0T | K18: =_xlfn.CONCAT(TEXT(SUMIFS(raw_output!$N$2:$N$197,raw_output!$M$2:$M$197,'Overall Output. Labeled'!$N18,raw_output!$A$2:$A$197,'Overall Output. Labeled'!$U18,raw_output!$B$2:$B$197,'Overall Output. Labeled'!$S18,raw_output!$C$2:$C$197,'Overall Output. Labeled'!$T18,raw_output!$D$2:$D$197,'Overall Output. Labeled'!$P18,raw_output!$E$2:$E$197,'Overall Output. Labeled'!$Q18,raw_output!$F$2:$F$197,'Overall Output. Labeled'!$R18),"$#.0"),"T") -> $83.6T | L18: =IF(W18>1000,_xlfn.CONCAT(TEXT(W18/1000,"#.#"),"M"),_xlfn.CONCAT(TEXT(W18,"#"),"k")) -> 12.9M | M18: =TEXT(SUMIFS(raw_output!$L$2:$L$197,raw_output!$M$2:$M$197,'Overall Output. Labeled'!$N18,raw_output!$A$2:$A$197,'Overall Output. Labeled'!$U18,raw_output!$B$2:$B$197,'Overall Output. Labeled'!$S18,raw_output!$C$2:$C$197,'Overall Output. Labeled'!$T18,raw_output!$D$2:$D$197,'Overall Output. Labeled'!$P18,raw_output!$E$2:$E$197,'Overall Output. Labeled'!$Q18,raw_output!$F$2:$F$197,'Overall Output. Labeled'!$R18),"$#.##") -> $4048.2 | N18: 0.035 | O18: 1 | P18: =F18*$O18 -> 5 | Q18: =G18*$O18 -> 5 | R18: 0.6 | S18: 10 | T18: 20 | U18: 40 | V18: =SUMIFS(raw_output!$K$2:$K$197,raw_output!$A$2:$A$197,'Overall Output. Labeled'!$U18,raw_output!$B$2:$B$197,'Overall Output. Labeled'!$S18,raw_output!$C$2:$C$197,'Overall Output. Labeled'!$T18,raw_output!$D$2:$D$197,'Overall Output. Labeled'!$P18,raw_output!$E$2:$E$197,'Overall Output. Labeled'!$Q18,raw_output!$F$2:$F$197,'Overall Output. Labeled'!$R18,raw_output!$M$2:$M$197,'Overall Output. Labeled'!$N18) -> 3951.0771 | W18: {=SUMIFS(raw_output!$J$2:$J$197,raw_output!$M$2:$M$197,'Overall Output. Labeled'!$N18,raw_output!$A$2:$A$197,'Overall Output. Labeled'!$U18,raw_output!$B$2:$B$197,'Overall Output. Labeled'!$S18,raw_output!$C$2:$C$197,'Overall Output. Labeled'!$T18,raw_output!$D$2:$D$197,'Overall Output. Labeled'!$P18,raw_output!$E$2:$E$197,'Overall Output. Labeled'!$Q18,raw_output!$F$2:$F$197,'Overall Output. Labeled'!$R18)*1000} -> 12900.835
A19: 11 | B19: NA | C19: Deploying existing Malaria vaccines | F19: NA | G19: NA | H19: NA | I19: NA | K19: $36.0T | N19: 0.02 | O19: 1 | S19: 10 | T19: 20 | U19: NA | V19: =SUMIFS(raw_output!$K$2:$K$197,raw_output!$A$2:$A$197,'Overall Output. Labeled'!$U19,raw_output!$B$2:$B$197,'Overall Output. Labeled'!$S19,raw_output!$C$2:$C$197,'Overall Output. Labeled'!$T19,raw_output!$D$2:$D$197,'Overall Output. Labeled'!$P19,raw_output!$E$2:$E$197,'Overall Output. Labeled'!$Q19,raw_output!$F$2:$F$197,'Overall Output. Labeled'!$R19,raw_output!$M$2:$M$197,'Overall Output. Labeled'!$N19) -> 0
A20: 11 | B20: NA | C20: Regular exercise | F20: 2.52 | G20: 1.26 | H20: 0 | I20: =CONCATENATE(U20,"+") -> 40+ | J20: =IF(V20>1000,_xlfn.CONCAT(TEXT(V20/1000,"$#.0"),"T"),_xlfn.CONCAT(TEXT(V20,"$#"),"B")) -> $715B | K20: =_xlfn.CONCAT(TEXT(SUMIFS(raw_output!$N$2:$N$197,raw_output!$M$2:$M$197,'Overall Output. Labeled'!$N20,raw_output!$A$2:$A$197,'Overall Output. Labeled'!$U20,raw_output!$B$2:$B$197,'Overall Output. Labeled'!$S20,raw_output!$C$2:$C$197,'Overall Output. Labeled'!$T20,raw_output!$D$2:$D$197,'Overall Output. Labeled'!$P20,raw_output!$E$2:$E$197,'Overall Output. Labeled'!$Q20,raw_output!$F$2:$F$197,'Overall Output. Labeled'!$R20),"$#.0"),"T") -> $38.4T | L20: =IF(W20>1000,_xlfn.CONCAT(TEXT(W20/1000,"#.#"),"M"),_xlfn.CONCAT(TEXT(W20,"#"),"k")) -> 6.5M | M20: =TEXT(SUMIFS(raw_output!$L$2:$L$197,raw_output!$M$2:$M$197,'Overall Output. Labeled'!$N20,raw_output!$A$2:$A$197,'Overall Output. Labeled'!$U20,raw_output!$B$2:$B$197,'Overall Output. Labeled'!$S20,raw_output!$C$2:$C$197,'Overall Output. Labeled'!$T20,raw_output!$D$2:$D$197,'Overall Output. Labeled'!$P20,raw_output!$E$2:$E$197,'Overall Output. Labeled'!$Q20,raw_output!$F$2:$F$197,'Overall Output. Labeled'!$R20),"$#.##") -> -$2229.5 | N20: 0.02 | O20: 1 | P20: =F20*$O20 -> 2.52 | Q20: 0 | R20: 0 | S20: 10 | T20: 20 | U20: 40 | V20: =SUMIFS(raw_output!$K$2:$K$197,raw_output!$A$2:$A$197,'Overall Output. Labeled'!$U20,raw_output!$B$2:$B$197,'Overall Output. Labeled'!$S20,raw_output!$C$2:$C$197,'Overall Output. Labeled'!$T20,raw_output!$D$2:$D$197,'Overall Output. Labeled'!$P20,raw_output!$E$2:$E$197,'Overall Output. Labeled'!$Q20,raw_output!$F$2:$F$197,'Overall Output. Labeled'!$R20,raw_output!$M$2:$M$197,'Overall Output. Labeled'!$N20) -> 714.84514 | W20: {=SUMIFS(raw_output!$J$2:$J$197,raw_output!$M$2:$M$197,'Overall Output. Labeled'!$N20,raw_output!$A$2:$A$197,'Overall Output. Labeled'!$U20,raw_output!$B$2:$B$197,'Overall Output. Labeled'!$S20,raw_output!$C$2:$C$197,'Overall Output. Labeled'!$T20,raw_output!$D$2:$D$197,'Overall Output. Labeled'!$P20,raw_output!$E$2:$E$197,'Overall Output. Labeled'!$Q20,raw_output!$F$2:$F$197,'Overall Output. Labeled'!$R20)*1000} -> 6529.4667
A21: 12 | B21: NA | C21: 41 the new 40, 100% adhere | F21: 1 | G21: 1 | H21: 1 | I21: =CONCATENATE(U21,"+") -> 40+ | J21: =IF(V21>1000,_xlfn.CONCAT(TEXT(V21/1000,"$#.0"),"T"),_xlfn.CONCAT(TEXT(V21,"$#"),"B")) -> $857B | K21: =_xlfn.CONCAT(TEXT(SUMIFS(raw_output!$N$2:$N$197,raw_output!$M$2:$M$197,'Overall Output. Labeled'!$N21,raw_output!$A$2:$A$197,'Overall Output. Labeled'!$U21,raw_output!$B$2:$B$197,'Overall Output. Labeled'!$S21,raw_output!$C$2:$C$197,'Overall Output. Labeled'!$T21,raw_output!$D$2:$D$197,'Overall Output. Labeled'!$P21,raw_output!$E$2:$E$197,'Overall Output. Labeled'!$Q21,raw_output!$F$2:$F$197,'Overall Output. Labeled'!$R21),"$#.0"),"T") -> $47.1T | L21: =IF(W21>1000,_xlfn.CONCAT(TEXT(W21/1000,"#.#"),"M"),_xlfn.CONCAT(TEXT(W21,"#"),"k")) -> 3.1M | M21: =TEXT(SUMIFS(raw_output!$L$2:$L$197,raw_output!$M$2:$M$197,'Overall Output. Labeled'!$N21,raw_output!$A$2:$A$197,'Overall Output. Labeled'!$U21,raw_output!$B$2:$B$197,'Overall Output. Labeled'!$S21,raw_output!$C$2:$C$197,'Overall Output. Labeled'!$T21,raw_output!$D$2:$D$197,'Overall Output. Labeled'!$P21,raw_output!$E$2:$E$197,'Overall Output. Labeled'!$Q21,raw_output!$F$2:$F$197,'Overall Output. Labeled'!$R21),"$#.##") -> $957.09 | N21: 0.02 | O21: 1 | P21: =F21*$O21 -> 1 | Q21: =G21*$O21 -> 1 | R21: 0.5 | S21: 10 | T21: 20 | U21: 40 | V21: =SUMIFS(raw_output!$K$2:$K$197,raw_output!$A$2:$A$197,'Overall Output. Labeled'!$U21,raw_output!$B$2:$B$197,'Overall Output. Labeled'!$S21,raw_output!$C$2:$C$197,'Overall Output. Labeled'!$T21,raw_output!$D$2:$D$197,'Overall Output. Labeled'!$P21,raw_output!$E$2:$E$197,'Overall Output. Labeled'!$Q21,raw_output!$F$2:$F$197,'Overall Output. Labeled'!$R21,raw_output!$M$2:$M$197,'Overall Output. Labeled'!$N21) -> 857.09418 | W21: {=SUMIFS(raw_output!$J$2:$J$197,raw_output!$M$2:$M$197,'Overall Output. Labeled'!$N21,raw_output!$A$2:$A$197,'Overall Output. Labeled'!$U21,raw_output!$B$2:$B$197,'Overall Output. Labeled'!$S21,raw_output!$C$2:$C$197,'Overall Output. Labeled'!$T21,raw_output!$D$2:$D$197,'Overall Output. Labeled'!$P21,raw_output!$E$2:$E$197,'Overall Output. Labeled'!$Q21,raw_output!$F$2:$F$197,'Overall Output. Labeled'!$R21)*1000} -> 3127.9637
A22: 12 | C22: 41 is the new 40, Scott et al | F22: 1 | G22: 1 | H22: 1 | I22: NA | K22: $46.8T | N22: 0.02 | S22: 10 | T22: 20 | U22: NA | V22: =SUMIFS(raw_output!$K$2:$K$197,raw_output!$A$2:$A$197,'Overall Output. Labeled'!$U22,raw_output!$B$2:$B$197,'Overall Output. Labeled'!$S22,raw_output!$C$2:$C$197,'Overall Output. Labeled'!$T22,raw_output!$D$2:$D$197,'Overall Output. Labeled'!$P22,raw_output!$E$2:$E$197,'Overall Output. Labeled'!$Q22,raw_output!$F$2:$F$197,'Overall Output. Labeled'!$R22,raw_output!$M$2:$M$197,'Overall Output. Labeled'!$N22) -> 0
A23: 12 | C23: 41 the new 40, 100% adhere, QALY | F23: 1 | G23: 1 | H23: 1 | I23: =CONCATENATE(U23,"+") -> 40+ | J23: =IF(V23>1000,_xlfn.CONCAT(TEXT(V23/1000,"$#.0"),"T"),_xlfn.CONCAT(TEXT(V23,"$#"),"B")) -> $857B | K23: =_xlfn.CONCAT(TEXT(SUMIFS(raw_output!$P$2:$P$197,raw_output!$M$2:$M$197,'Overall Output. Labeled'!$N21,raw_output!$A$2:$A$197,'Overall Output. Labeled'!$U21,raw_output!$B$2:$B$197,'Overall Output. Labeled'!$S21,raw_output!$C$2:$C$197,'Overall Output. Labeled'!$T21,raw_output!$D$2:$D$197,'Overall Output. Labeled'!$P21,raw_output!$E$2:$E$197,'Overall Output. Labeled'!$Q21,raw_output!$F$2:$F$197,'Overall Output. Labeled'!$R21),"$#.0"),"T") -> $28.4T | L23: =IF(W23>1000,_xlfn.CONCAT(TEXT(W23/1000,"#.#"),"M"),_xlfn.CONCAT(TEXT(W23,"#"),"k")) -> 3.1M | M23: =TEXT(SUMIFS(raw_output!$L$2:$L$197,raw_output!$M$2:$M$197,'Overall Output. Labeled'!$N23,raw_output!$A$2:$A$197,'Overall Output. Labeled'!$U23,raw_output!$B$2:$B$197,'Overall Output. Labeled'!$S23,raw_output!$C$2:$C$197,'Overall Output. Labeled'!$T23,raw_output!$D$2:$D$197,'Overall Output. Labeled'!$P23,raw_output!$E$2:$E$197,'Overall Output. Labeled'!$Q23,raw_output!$F$2:$F$197,'Overall Output. Labeled'!$R23),"$#.##") -> $957.09 | N23: 0.02 | O23: 1 | P23: =F23*$O23 -> 1 | Q23: =G23*$O23 -> 1 | R23: 0.5 | S23: 10 | T23: 20 | U23: 40 | V23: =SUMIFS(raw_output!$K$2:$K$197,raw_output!$A$2:$A$197,'Overall Output. Labeled'!$U23,raw_output!$B$2:$B$197,'Overall Output. Labeled'!$S23,raw_output!$C$2:$C$197,'Overall Output. Labeled'!$T23,raw_output!$D$2:$D$197,'Overall Output. Labeled'!$P23,raw_output!$E$2:$E$197,'Overall Output. Labeled'!$Q23,raw_output!$F$2:$F$197,'Overall Output. Labeled'!$R23,raw_output!$M$2:$M$197,'Overall Output. Labeled'!$N23) -> 857.09418 | W23: {=SUMIFS(raw_output!$J$2:$J$197,raw_output!$M$2:$M$197,'Overall Output. Labeled'!$N23,raw_output!$A$2:$A$197,'Overall Output. Labeled'!$U23,raw_output!$B$2:$B$197,'Overall Output. Labeled'!$S23,raw_output!$C$2:$C$197,'Overall Output. Labeled'!$T23,raw_output!$D$2:$D$197,'Overall Output. Labeled'!$P23,raw_output!$E$2:$E$197,'Overall Output. Labeled'!$Q23,raw_output!$F$2:$F$197,'Overall Output. Labeled'!$R23)*1000} -> 3127.9637
A24: Appendix | C24: 1 yr shift in mortality | F24: 1 | G24: 0 | H24: 0 | I24: =CONCATENATE(U24,"+") -> 40+ | J24: =IF(V24>1000,_xlfn.CONCAT(TEXT(V24/1000,"$#.0"),"T"),_xlfn.CONCAT(TEXT(V24,"$#"),"B")) -> $137B | K24: =_xlfn.CONCAT(TEXT(SUMIFS(raw_output!$N$2:$N$197,raw_output!$M$2:$M$197,'Overall Output. Labeled'!$N24,raw_output!$A$2:$A$197,'Overall Output. Labeled'!$U24,raw_output!$B$2:$B$197,'Overall Output. Labeled'!$S24,raw_output!$C$2:$C$197,'Overall Output. Labeled'!$T24,raw_output!$D$2:$D$197,'Overall Output. Labeled'!$P24,raw_output!$E$2:$E$197,'Overall Output. Labeled'!$Q24,raw_output!$F$2:$F$197,'Overall Output. Labeled'!$R24),"$#.0"),"T") -> $7.8T | L24: =IF(W24>1000,_xlfn.CONCAT(TEXT(W24/1000,"#.#"),"M"),_xlfn.CONCAT(TEXT(W24,"#"),"k")) -> 1.4M | M24: =TEXT(SUMIFS(raw_output!$L$2:$L$197,raw_output!$M$2:$M$197,'Overall Output. Labeled'!$N24,raw_output!$A$2:$A$197,'Overall Output. Labeled'!$U24,raw_output!$B$2:$B$197,'Overall Output. Labeled'!$S24,raw_output!$C$2:$C$197,'Overall Output. Labeled'!$T24,raw_output!$D$2:$D$197,'Overall Output. Labeled'!$P24,raw_output!$E$2:$E$197,'Overall Output. Labeled'!$Q24,raw_output!$F$2:$F$197,'Overall Output. Labeled'!$R24),"$#.##") -> -$489.4 | N24: 0.02 | O24: 0.5 | P24: =F24*$O24 -> 0.5 | Q24: =G24*$O24 -> 0 | R24: =H24*$O24 -> 0 | S24: 10 | T24: 20 | U24: 40 | V24: =SUMIFS(raw_output!$K$2:$K$197,raw_output!$A$2:$A$197,'Overall Output. Labeled'!$U24,raw_output!$B$2:$B$197,'Overall Output. Labeled'!$S24,raw_output!$C$2:$C$197,'Overall Output. Labeled'!$T24,raw_output!$D$2:$D$197,'Overall Output. Labeled'!$P24,raw_output!$E$2:$E$197,'Overall Output. Labeled'!$Q24,raw_output!$F$2:$F$197,'Overall Output. Labeled'!$R24,raw_output!$M$2:$M$197,'Overall Output. Labeled'!$N24) -> 137.08382 | W24: {=SUMIFS(raw_output!$J$2:$J$197,raw_output!$M$2:$M$197,'Overall Output. Labeled'!$N24,raw_output!$A$2:$A$197,'Overall Output. Labeled'!$U24,raw_output!$B$2:$B$197,'Overall Output. Labeled'!$S24,raw_output!$C$2:$C$197,'Overall Output. Labeled'!$T24,raw_output!$D$2:$D$197,'Overall Output. Labeled'!$P24,raw_output!$E$2:$E$197,'Overall Output. Labeled'!$Q24,raw_output!$F$2:$F$197,'Overall Output. Labeled'!$R24)*1000} -> 1358.5421
A25: Appendix | C25: 1 year shift in productivity | F25: 0 | G25: 1 | H25: 0 | I25: =CONCATENATE(U25,"+") -> 40+ | J25: =IF(V25>1000,_xlfn.CONCAT(TEXT(V25/1000,"$#.0"),"T"),_xlfn.CONCAT(TEXT(V25,"$#"),"B")) -> $252B | K25: =_xlfn.CONCAT(TEXT(SUMIFS(raw_output!$N$2:$N$197,raw_output!$M$2:$M$197,'Overall Output. Labeled'!$N25,raw_output!$A$2:$A$197,'Overall Output. Labeled'!$U25,raw_output!$B$2:$B$197,'Overall Output. Labeled'!$S25,raw_output!$C$2:$C$197,'Overall Output. Labeled'!$T25,raw_output!$D$2:$D$197,'Overall Output. Labeled'!$P25,raw_output!$E$2:$E$197,'Overall Output. Labeled'!$Q25,raw_output!$F$2:$F$197,'Overall Output. Labeled'!$R25),"$#.0"),"T") -> $10.6T | L25: =IF(W25>1000,_xlfn.CONCAT(TEXT(W25/1000,"#.#"),"M"),_xlfn.CONCAT(TEXT(W25,"#"),"k")) -> k | M25: =TEXT(SUMIFS(raw_output!$L$2:$L$197,raw_output!$M$2:$M$197,'Overall Output. Labeled'!$N25,raw_output!$A$2:$A$197,'Overall Output. Labeled'!$U25,raw_output!$B$2:$B$197,'Overall Output. Labeled'!$S25,raw_output!$C$2:$C$197,'Overall Output. Labeled'!$T25,raw_output!$D$2:$D$197,'Overall Output. Labeled'!$P25,raw_output!$E$2:$E$197,'Overall Output. Labeled'!$Q25,raw_output!$F$2:$F$197,'Overall Output. Labeled'!$R25),"$#.##") -> $875.24 | N25: 0.02 | O25: 0.5 | P25: =F25*$O25 -> 0 | Q25: =G25*$O25 -> 0.5 | R25: =H25*$O25 -> 0 | S25: 10 | T25: 20 | U25: 40 | V25: =SUMIFS(raw_output!$K$2:$K$197,raw_output!$A$2:$A$197,'Overall Output. Labeled'!$U25,raw_output!$B$2:$B$197,'Overall Output. Labeled'!$S25,raw_output!$C$2:$C$197,'Overall Output. Labeled'!$T25,raw_output!$D$2:$D$197,'Overall Output. Labeled'!$P25,raw_output!$E$2:$E$197,'Overall Output. Labeled'!$Q25,raw_output!$F$2:$F$197,'Overall Output. Labeled'!$R25,raw_output!$M$2:$M$197,'Overall Output. Labeled'!$N25) -> 252.27253 | W25: {=SUMIFS(raw_output!$J$2:$J$197,raw_output!$M$2:$M$197,'Overall Output. Labeled'!$N25,raw_output!$A$2:$A$197,'Overall Output. Labeled'!$U25,raw_output!$B$2:$B$197,'Overall Output. Labeled'!$S25,raw_output!$C$2:$C$197,'Overall Output. Labeled'!$T25,raw_output!$D$2:$D$197,'Overall Output. Labeled'!$P25,raw_output!$E$2:$E$197,'Overall Output. Labeled'!$Q25,raw_output!$F$2:$F$197,'Overall Output. Labeled'!$R25)*1000} -> 0
A26: Appendix | C26: 1 year shift in fertility | F26: 0 | G26: 0 | H26: 1 | I26: =CONCATENATE(U26,"+") -> 40+ | J26: =IF(V26>1000,_xlfn.CONCAT(TEXT(V26/1000,"$#.0"),"T"),_xlfn.CONCAT(TEXT(V26,"$#"),"B")) -> -$21B | K26: =_xlfn.CONCAT(TEXT(SUMIFS(raw_output!$N$2:$N$197,raw_output!$M$2:$M$197,'Overall Output. Labeled'!$N26,raw_output!$A$2:$A$197,'Overall Output. Labeled'!$U26,raw_output!$B$2:$B$197,'Overall Output. Labeled'!$S26,raw_output!$C$2:$C$197,'Overall Output. Labeled'!$T26,raw_output!$D$2:$D$197,'Overall Output. Labeled'!$P26,raw_output!$E$2:$E$197,'Overall Output. Labeled'!$Q26,raw_output!$F$2:$F$197,'Overall Output. Labeled'!$R26),"$#.0"),"T") -> $8.0T | L26: =IF(W26>1000,_xlfn.CONCAT(TEXT(W26/1000,"#.#"),"M"),_xlfn.CONCAT(TEXT(W26,"#"),"k")) -> 365k | M26: =TEXT(SUMIFS(raw_output!$L$2:$L$197,raw_output!$M$2:$M$197,'Overall Output. Labeled'!$N26,raw_output!$A$2:$A$197,'Overall Output. Labeled'!$U26,raw_output!$B$2:$B$197,'Overall Output. Labeled'!$S26,raw_output!$C$2:$C$197,'Overall Output. Labeled'!$T26,raw_output!$D$2:$D$197,'Overall Output. Labeled'!$P26,raw_output!$E$2:$E$197,'Overall Output. Labeled'!$Q26,raw_output!$F$2:$F$197,'Overall Output. Labeled'!$R26),"$#.##") -> -$89.29 | N26: 0.02 | O26: 0.5 | P26: =F26*$O26 -> 0 | Q26: =G26*$O26 -> 0 | R26: =H26*$O26 -> 0.5 | S26: 10 | T26: 20 | U26: 40 | V26: =SUMIFS(raw_output!$K$2:$K$197,raw_output!$A$2:$A$197,'Overall Output. Labeled'!$U26,raw_output!$B$2:$B$197,'Overall Output. Labeled'!$S26,raw_output!$C$2:$C$197,'Overall Output. Labeled'!$T26,raw_output!$D$2:$D$197,'Overall Output. Labeled'!$P26,raw_output!$E$2:$E$197,'Overall Output. Labeled'!$Q26,raw_output!$F$2:$F$197,'Overall Output. Labeled'!$R26,raw_output!$M$2:$M$197,'Overall Output. Labeled'!$N26) -> -20.679367 | W26: {=SUMIFS(raw_output!$J$2:$J$197,raw_output!$M$2:$M$197,'Overall Output. Labeled'!$N26,raw_output!$A$2:$A$197,'Overall Output. Labeled'!$U26,raw_output!$B$2:$B$197,'Overall Output. Labeled'!$S26,raw_output!$C$2:$C$197,'Overall Output. Labeled'!$T26,raw_output!$D$2:$D$197,'Overall Output. Labeled'!$P26,raw_output!$E$2:$E$197,'Overall Output. Labeled'!$Q26,raw_output!$F$2:$F$197,'Overall Output. Labeled'!$R26)*1000} -> 364.63356
A27: Appendix | C27: 1% decrease in mortality | I27: =CONCATENATE(U27,"+") -> 40+ | J27: =IF(V27>1000,_xlfn.CONCAT(TEXT(V27/1000,"$#.0"),"T"),_xlfn.CONCAT(TEXT(V27,"$#"),"B")) -> $22B | K27: =_xlfn.CONCAT(TEXT(SUMIFS(raw_output!$N$2:$N$197,raw_output!$M$2:$M$197,'Overall Output. Labeled'!$N27,raw_output!$A$2:$A$197,'Overall Output. Labeled'!$U27,raw_output!$B$2:$B$197,'Overall Output. Labeled'!$S27,raw_output!$C$2:$C$197,'Overall Output. Labeled'!$T27,raw_output!$D$2:$D$197,'Overall Output. Labeled'!$P27,raw_output!$E$2:$E$197,'Overall Output. Labeled'!$Q27,raw_output!$F$2:$F$197,'Overall Output. Labeled'!$R27),"$#.0"),"T") -> $1.8T | L27: =IF(W27>1000,_xlfn.CONCAT(TEXT(W27/1000,"#.#"),"M"),_xlfn.CONCAT(TEXT(W27,"#"),"k")) -> 349k | M27: =TEXT(SUMIFS(raw_output!$L$2:$L$197,raw_output!$M$2:$M$197,'Overall Output. Labeled'!$N27,raw_output!$A$2:$A$197,'Overall Output. Labeled'!$U27,raw_output!$B$2:$B$197,'Overall Output. Labeled'!$S27,raw_output!$C$2:$C$197,'Overall Output. Labeled'!$T27,raw_output!$D$2:$D$197,'Overall Output. Labeled'!$P27,raw_output!$E$2:$E$197,'Overall Output. Labeled'!$Q27,raw_output!$F$2:$F$197,'Overall Output. Labeled'!$R27),"$#.##") -> -$170.95 | N27: 0.02 | O27: 1 | P27: 0.13 | Q27: =G27 -> 0 | R27: =H27 -> 0 | S27: 10 | T27: 20 | U27: 40 | V27: =SUMIFS(raw_output!$K$2:$K$197,raw_output!$A$2:$A$197,'Overall Output. Labeled'!$U27,raw_output!$B$2:$B$197,'Overall Output. Labeled'!$S27,raw_output!$C$2:$C$197,'Overall Output. Labeled'!$T27,raw_output!$D$2:$D$197,'Overall Output. Labeled'!$P27,raw_output!$E$2:$E$197,'Overall Output. Labeled'!$Q27,raw_output!$F$2:$F$197,'Overall Output. Labeled'!$R27,raw_output!$M$2:$M$197,'Overall Output. Labeled'!$N27) -> 21.61646 | W27: {=SUMIFS(raw_output!$J$2:$J$197,raw_output!$M$2:$M$197,'Overall Output. Labeled'!$N27,raw_output!$A$2:$A$197,'Overall Output. Labeled'!$U27,raw_output!$B$2:$B$197,'Overall Output. Labeled'!$S27,raw_output!$C$2:$C$197,'Overall Output. Labeled'!$T27,raw_output!$D$2:$D$197,'Overall Output. Labeled'!$P27,raw_output!$E$2:$E$197,'Overall Output. Labeled'!$Q27,raw_output!$F$2:$F$197,'Overall Output. Labeled'!$R27)*1000} -> 348.91063
A28: Appendix | C28: 1% increase in productivity | I28: =CONCATENATE(U28,"+") -> 40+ | J28: =IF(V28>1000,_xlfn.CONCAT(TEXT(V28/1000,"$#.0"),"T"),_xlfn.CONCAT(TEXT(V28,"$#"),"B")) -> $236B | K28: =_xlfn.CONCAT(TEXT(SUMIFS(raw_output!$N$2:$N$197,raw_output!$M$2:$M$197,'Overall Output. Labeled'!$N28,raw_output!$A$2:$A$197,'Overall Output. Labeled'!$U28,raw_output!$B$2:$B$197,'Overall Output. Labeled'!$S28,raw_output!$C$2:$C$197,'Overall Output. Labeled'!$T28,raw_output!$D$2:$D$197,'Overall Output. Labeled'!$P28,raw_output!$E$2:$E$197,'Overall Output. Labeled'!$Q28,raw_output!$F$2:$F$197,'Overall Output. Labeled'!$R28),"$#.0"),"T") -> $9.9T | L28: =IF(W28>1000,_xlfn.CONCAT(TEXT(W28/1000,"#.#"),"M"),_xlfn.CONCAT(TEXT(W28,"#"),"k")) -> k | M28: =TEXT(SUMIFS(raw_output!$L$2:$L$197,raw_output!$M$2:$M$197,'Overall Output. Labeled'!$N28,raw_output!$A$2:$A$197,'Overall Output. Labeled'!$U28,raw_output!$B$2:$B$197,'Overall Output. Labeled'!$S28,raw_output!$C$2:$C$197,'Overall Output. Labeled'!$T28,raw_output!$D$2:$D$197,'Overall Output. Labeled'!$P28,raw_output!$E$2:$E$197,'Overall Output. Labeled'!$Q28,raw_output!$F$2:$F$197,'Overall Output. Labeled'!$R28),"$#.##") -> $818.1 | N28: 0.02 | O28: 1 | P28: =F28 -> 0 | Q28: 0.47 | R28: =H28 -> 0 | S28: 10 | T28: 20 | U28: 40 | V28: =SUMIFS(raw_output!$K$2:$K$197,raw_output!$A$2:$A$197,'Overall Output. Labeled'!$U28,raw_output!$B$2:$B$197,'Overall Output. Labeled'!$S28,raw_output!$C$2:$C$197,'Overall Output. Labeled'!$T28,raw_output!$D$2:$D$197,'Overall Output. Labeled'!$P28,raw_output!$E$2:$E$197,'Overall Output. Labeled'!$Q28,raw_output!$F$2:$F$197,'Overall Output. Labeled'!$R28,raw_output!$M$2:$M$197,'Overall Output. Labeled'!$N28) -> 235.76946 | W28: {=SUMIFS(raw_output!$J$2:$J$197,raw_output!$M$2:$M$197,'Overall Output. Labeled'!$N28,raw_output!$A$2:$A$197,'Overall Output. Labeled'!$U28,raw_output!$B$2:$B$197,'Overall Output. Labeled'!$S28,raw_output!$C$2:$C$197,'Overall Output. Labeled'!$T28,raw_output!$D$2:$D$197,'Overall Output. Labeled'!$P28,raw_output!$E$2:$E$197,'Overall Output. Labeled'!$Q28,raw_output!$F$2:$F$197,'Overall Output. Labeled'!$R28)*1000} -> 0
A29: Appendix | C29: 1% increase in fertility | I29: =CONCATENATE(U29,"+") -> 40+ | J29: =IF(V29>1000,_xlfn.CONCAT(TEXT(V29/1000,"$#.0"),"T"),_xlfn.CONCAT(TEXT(V29,"$#"),"B")) -> -$21B | K29: =_xlfn.CONCAT(TEXT(SUMIFS(raw_output!$N$2:$N$197,raw_output!$M$2:$M$197,'Overall Output. Labeled'!$N29,raw_output!$A$2:$A$197,'Overall Output. Labeled'!$U29,raw_output!$B$2:$B$197,'Overall Output. Labeled'!$S29,raw_output!$C$2:$C$197,'Overall Output. Labeled'!$T29,raw_output!$D$2:$D$197,'Overall Output. Labeled'!$P29,raw_output!$E$2:$E$197,'Overall Output. Labeled'!$Q29,raw_output!$F$2:$F$197,'Overall Output. Labeled'!$R29),"$#.0"),"T") -> $8.7T | L29: =IF(W29>1000,_xlfn.CONCAT(TEXT(W29/1000,"#.#"),"M"),_xlfn.CONCAT(TEXT(W29,"#"),"k")) -> 394k | M29: =TEXT(SUMIFS(raw_output!$L$2:$L$197,raw_output!$M$2:$M$197,'Overall Output. Labeled'!$N29,raw_output!$A$2:$A$197,'Overall Output. Labeled'!$U29,raw_output!$B$2:$B$197,'Overall Output. Labeled'!$S29,raw_output!$C$2:$C$197,'Overall Output. Labeled'!$T29,raw_output!$D$2:$D$197,'Overall Output. Labeled'!$P29,raw_output!$E$2:$E$197,'Overall Output. Labeled'!$Q29,raw_output!$F$2:$F$197,'Overall Output. Labeled'!$R29),"$#.##") -> -$91.44 | N29: 0.02 | O29: 1 | P29: =F29 -> 0 | Q29: =G29 -> 0 | R29: 0.54 | S29: 10 | T29: 20 | U29: 40 | V29: =SUMIFS(raw_output!$K$2:$K$197,raw_output!$A$2:$A$197,'Overall Output. Labeled'!$U29,raw_output!$B$2:$B$197,'Overall Output. Labeled'!$S29,raw_output!$C$2:$C$197,'Overall Output. Labeled'!$T29,raw_output!$D$2:$D$197,'Overall Output. Labeled'!$P29,raw_output!$E$2:$E$197,'Overall Output. Labeled'!$Q29,raw_output!$F$2:$F$197,'Overall Output. Labeled'!$R29,raw_output!$M$2:$M$197,'Overall Output. Labeled'!$N29) -> -20.851594 | W29: {=SUMIFS(raw_output!$J$2:$J$197,raw_output!$M$2:$M$197,'Overall Output. Labeled'!$N29,raw_output!$A$2:$A$197,'Overall Output. Labeled'!$U29,raw_output!$B$2:$B$197,'Overall Output. Labeled'!$S29,raw_output!$C$2:$C$197,'Overall Output. Labeled'!$T29,raw_output!$D$2:$D$197,'Overall Output. Labeled'!$P29,raw_output!$E$2:$E$197,'Overall Output. Labeled'!$Q29,raw_output!$F$2:$F$197,'Overall Output. Labeled'!$R29)*1000} -> 393.80424
A30: Appendix | C30: 1% increase in all 3 channels | I30: =CONCATENATE(U30,"+") -> 40+ | J30: =IF(V30>1000,_xlfn.CONCAT(TEXT(V30/1000,"$#.0"),"T"),_xlfn.CONCAT(TEXT(V30,"$#"),"B")) -> $274B | K30: =_xlfn.CONCAT(TEXT(SUMIFS(raw_output!$N$2:$N$197,raw_output!$M$2:$M$197,'Overall Output. Labeled'!$N30,raw_output!$A$2:$A$197,'Overall Output. Labeled'!$U30,raw_output!$B$2:$B$197,'Overall Output. Labeled'!$S30,raw_output!$C$2:$C$197,'Overall Output. Labeled'!$T30,raw_output!$D$2:$D$197,'Overall Output. Labeled'!$P30,raw_output!$E$2:$E$197,'Overall Output. Labeled'!$Q30,raw_output!$F$2:$F$197,'Overall Output. Labeled'!$R30),"$#.0"),"T") -> $21.0T | L30: =IF(W30>1000,_xlfn.CONCAT(TEXT(W30/1000,"#.#"),"M"),_xlfn.CONCAT(TEXT(W30,"#"),"k")) -> 743k | M30: =TEXT(SUMIFS(raw_output!$L$2:$L$197,raw_output!$M$2:$M$197,'Overall Output. Labeled'!$N30,raw_output!$A$2:$A$197,'Overall Output. Labeled'!$U30,raw_output!$B$2:$B$197,'Overall Output. Labeled'!$S30,raw_output!$C$2:$C$197,'Overall Output. Labeled'!$T30,raw_output!$D$2:$D$197,'Overall Output. Labeled'!$P30,raw_output!$E$2:$E$197,'Overall Output. Labeled'!$Q30,raw_output!$F$2:$F$197,'Overall Output. Labeled'!$R30),"$#.##") -> $681.02 | N30: 0.02 | O30: 1 | P30: 0.13 | Q30: 0.47 | R30: 0.54 | S30: 10 | T30: 20 | U30: 40 | V30: =SUMIFS(raw_output!$K$2:$K$197,raw_output!$A$2:$A$197,'Overall Output. Labeled'!$U30,raw_output!$B$2:$B$197,'Overall Output. Labeled'!$S30,raw_output!$C$2:$C$197,'Overall Output. Labeled'!$T30,raw_output!$D$2:$D$197,'Overall Output. Labeled'!$P30,raw_output!$E$2:$E$197,'Overall Output. Labeled'!$Q30,raw_output!$F$2:$F$197,'Overall Output. Labeled'!$R30,raw_output!$M$2:$M$197,'Overall Output. Labeled'!$N30) -> 274.0875 | W30: {=SUMIFS(raw_output!$J$2:$J$197,raw_output!$M$2:$M$197,'Overall Output. Labeled'!$N30,raw_output!$A$2:$A$197,'Overall Output. Labeled'!$U30,raw_output!$B$2:$B$197,'Overall Output. Labeled'!$S30,raw_output!$C$2:$C$197,'Overall Output. Labeled'!$T30,raw_output!$D$2:$D$197,'Overall Output. Labeled'!$P30,raw_output!$E$2:$E$197,'Overall Output. Labeled'!$Q30,raw_output!$F$2:$F$197,'Overall Output. Labeled'!$R30)*1000} -> 742.72155
A31: Appendix | C31: 41 is the new 40, 1% discount | F31: 1 | G31: 1 | H31: 1 | I31: =CONCATENATE(U31,"+") -> 40+ | J31: =IF(V31>1000,_xlfn.CONCAT(TEXT(V31/1000,"$#.0"),"T"),_xlfn.CONCAT(TEXT(V31,"$#"),"B")) -> $408B | K31: =_xlfn.CONCAT(TEXT(SUMIFS(raw_output!$N$2:$N$197,raw_output!$M$2:$M$197,'Overall Output. Labeled'!$N31,raw_output!$A$2:$A$197,'Overall Output. Labeled'!$U31,raw_output!$B$2:$B$197,'Overall Output. Labeled'!$S31,raw_output!$C$2:$C$197,'Overall Output. Labeled'!$T31,raw_output!$D$2:$D$197,'Overall Output. Labeled'!$P31,raw_output!$E$2:$E$197,'Overall Output. Labeled'!$Q31,raw_output!$F$2:$F$197,'Overall Output. Labeled'!$R31),"$#.0"),"T") -> $53.3T | L31: =IF(W31>1000,_xlfn.CONCAT(TEXT(W31/1000,"#.#"),"M"),_xlfn.CONCAT(TEXT(W31,"#"),"k")) -> 1.7M | M31: =TEXT(SUMIFS(raw_output!$L$2:$L$197,raw_output!$M$2:$M$197,'Overall Output. Labeled'!$N31,raw_output!$A$2:$A$197,'Overall Output. Labeled'!$U31,raw_output!$B$2:$B$197,'Overall Output. Labeled'!$S31,raw_output!$C$2:$C$197,'Overall Output. Labeled'!$T31,raw_output!$D$2:$D$197,'Overall Output. Labeled'!$P31,raw_output!$E$2:$E$197,'Overall Output. Labeled'!$Q31,raw_output!$F$2:$F$197,'Overall Output. Labeled'!$R31),"$#.##") -> $425.39 | N31: 0.01 | O31: 0.5 | P31: =F31*$O31 -> 0.5 | Q31: =G31*$O31 -> 0.5 | R31: =H31*$O31 -> 0.5 | S31: 10 | T31: 20 | U31: 40 | V31: =SUMIFS(raw_output!$K$2:$K$197,raw_output!$A$2:$A$197,'Overall Output. Labeled'!$U31,raw_output!$B$2:$B$197,'Overall Output. Labeled'!$S31,raw_output!$C$2:$C$197,'Overall Output. Labeled'!$T31,raw_output!$D$2:$D$197,'Overall Output. Labeled'!$P31,raw_output!$E$2:$E$197,'Overall Output. Labeled'!$Q31,raw_output!$F$2:$F$197,'Overall Output. Labeled'!$R31,raw_output!$M$2:$M$197,'Overall Output. Labeled'!$N31) -> 408.38262 | W31: {=SUMIFS(raw_output!$J$2:$J$197,raw_output!$M$2:$M$197,'Overall Output. Labeled'!$N31,raw_output!$A$2:$A$197,'Overall Output. Labeled'!$U31,raw_output!$B$2:$B$197,'Overall Output. Labeled'!$S31,raw_output!$C$2:$C$197,'Overall Output. Labeled'!$T31,raw_output!$D$2:$D$197,'Overall Output. Labeled'!$P31,raw_output!$E$2:$E$197,'Overall Output. Labeled'!$Q31,raw_output!$F$2:$F$197,'Overall Output. Labeled'!$R31)*1000} -> 1723.1995
A32: Appendix | C32: 41 is the new 40, 3% discount | F32: 1 | G32: 1 | H32: 1 | I32: =CONCATENATE(U32,"+") -> 40+ | J32: =IF(V32>1000,_xlfn.CONCAT(TEXT(V32/1000,"$#.0"),"T"),_xlfn.CONCAT(TEXT(V32,"$#"),"B")) -> $408B | K32: =_xlfn.CONCAT(TEXT(SUMIFS(raw_output!$N$2:$N$197,raw_output!$M$2:$M$197,'Overall Output. Labeled'!$N32,raw_output!$A$2:$A$197,'Overall Output. Labeled'!$U32,raw_output!$B$2:$B$197,'Overall Output. Labeled'!$S32,raw_output!$C$2:$C$197,'Overall Output. Labeled'!$T32,raw_output!$D$2:$D$197,'Overall Output. Labeled'!$P32,raw_output!$E$2:$E$197,'Overall Output. Labeled'!$Q32,raw_output!$F$2:$F$197,'Overall Output. Labeled'!$R32),"$#.0"),"T") -> $14.6T | L32: =IF(W32>1000,_xlfn.CONCAT(TEXT(W32/1000,"#.#"),"M"),_xlfn.CONCAT(TEXT(W32,"#"),"k")) -> 1.7M | M32: =TEXT(SUMIFS(raw_output!$L$2:$L$197,raw_output!$M$2:$M$197,'Overall Output. Labeled'!$N32,raw_output!$A$2:$A$197,'Overall Output. Labeled'!$U32,raw_output!$B$2:$B$197,'Overall Output. Labeled'!$S32,raw_output!$C$2:$C$197,'Overall Output. Labeled'!$T32,raw_output!$D$2:$D$197,'Overall Output. Labeled'!$P32,raw_output!$E$2:$E$197,'Overall Output. Labeled'!$Q32,raw_output!$F$2:$F$197,'Overall Output. Labeled'!$R32),"$#.##") -> $425.39 | N32: 0.03 | O32: 0.5 | P32: =F32*$O32 -> 0.5 | Q32: =G32*$O32 -> 0.5 | R32: =H32*$O32 -> 0.5 | S32: 10 | T32: 20 | U32: 40 | V32: =SUMIFS(raw_output!$K$2:$K$197,raw_output!$A$2:$A$197,'Overall Output. Labeled'!$U32,raw_output!$B$2:$B$197,'Overall Output. Labeled'!$S32,raw_output!$C$2:$C$197,'Overall Output. Labeled'!$T32,raw_output!$D$2:$D$197,'Overall Output. Labeled'!$P32,raw_output!$E$2:$E$197,'Overall Output. Labeled'!$Q32,raw_output!$F$2:$F$197,'Overall Output. Labeled'!$R32,raw_output!$M$2:$M$197,'Overall Output. Labeled'!$N32) -> 408.38262 | W32: {=SUMIFS(raw_output!$J$2:$J$197,raw_output!$M$2:$M$197,'Overall Output. Labeled'!$N32,raw_output!$A$2:$A$197,'Overall Output. Labeled'!$U32,raw_output!$B$2:$B$197,'Overall Output. Labeled'!$S32,raw_output!$C$2:$C$197,'Overall Output. Labeled'!$T32,raw_output!$D$2:$D$197,'Overall Output. Labeled'!$P32,raw_output!$E$2:$E$197,'Overall Output. Labeled'!$Q32,raw_output!$F$2:$F$197,'Overall Output. Labeled'!$R32)*1000} -> 1723.1995
A33: Appendix | C33: 41 is the new 40, 4% discount | F33: 1 | G33: 1 | H33: 1 | I33: =CONCATENATE(U33,"+") -> 40+ | J33: =IF(V33>1000,_xlfn.CONCAT(TEXT(V33/1000,"$#.0"),"T"),_xlfn.CONCAT(TEXT(V33,"$#"),"B")) -> $408B | K33: =_xlfn.CONCAT(TEXT(SUMIFS(raw_output!$N$2:$N$197,raw_output!$M$2:$M$197,'Overall Output. Labeled'!$N33,raw_output!$A$2:$A$197,'Overall Output. Labeled'!$U33,raw_output!$B$2:$B$197,'Overall Output. Labeled'!$S33,raw_output!$C$2:$C$197,'Overall Output. Labeled'!$T33,raw_output!$D$2:$D$197,'Overall Output. Labeled'!$P33,raw_output!$E$2:$E$197,'Overall Output. Labeled'!$Q33,raw_output!$F$2:$F$197,'Overall Output. Labeled'!$R33),"$#.0"),"T") -> $8.3T | L33: =IF(W33>1000,_xlfn.CONCAT(TEXT(W33/1000,"#.#"),"M"),_xlfn.CONCAT(TEXT(W33,"#"),"k")) -> 1.7M | M33: =TEXT(SUMIFS(raw_output!$L$2:$L$197,raw_output!$M$2:$M$197,'Overall Output. Labeled'!$N33,raw_output!$A$2:$A$197,'Overall Output. Labeled'!$U33,raw_output!$B$2:$B$197,'Overall Output. Labeled'!$S33,raw_output!$C$2:$C$197,'Overall Output. Labeled'!$T33,raw_output!$D$2:$D$197,'Overall Output. Labeled'!$P33,raw_output!$E$2:$E$197,'Overall Output. Labeled'!$Q33,raw_output!$F$2:$F$197,'Overall Output. Labeled'!$R33),"$#.##") -> $425.39 | N33: 0.04 | O33: 0.5 | P33: =F33*$O33 -> 0.5 | Q33: =G33*$O33 -> 0.5 | R33: =H33*$O33 -> 0.5 | S33: 10 | T33: 20 | U33: 40 | V33: =SUMIFS(raw_output!$K$2:$K$197,raw_output!$A$2:$A$197,'Overall Output. Labeled'!$U33,raw_output!$B$2:$B$197,'Overall Output. Labeled'!$S33,raw_output!$C$2:$C$197,'Overall Output. Labeled'!$T33,raw_output!$D$2:$D$197,'Overall Output. Labeled'!$P33,raw_output!$E$2:$E$197,'Overall Output. Labeled'!$Q33,raw_output!$F$2:$F$197,'Overall Output. Labeled'!$R33,raw_output!$M$2:$M$197,'Overall Output. Labeled'!$N33) -> 408.38262 | W33: {=SUMIFS(raw_output!$J$2:$J$197,raw_output!$M$2:$M$197,'Overall Output. Labeled'!$N33,raw_output!$A$2:$A$197,'Overall Output. Labeled'!$U33,raw_output!$B$2:$B$197,'Overall Output. Labeled'!$S33,raw_output!$C$2:$C$197,'Overall Output. Labeled'!$T33,raw_output!$D$2:$D$197,'Overall Output. Labeled'!$P33,raw_output!$E$2:$E$197,'Overall Output. Labeled'!$Q33,raw_output!$F$2:$F$197,'Overall Output. Labeled'!$R33)*1000} -> 1723.1995
A34: Appendix | C34: 41 is the new 40, 5% discount | F34: 1 | G34: 1 | H34: 1 | I34: =CONCATENATE(U34,"+") -> 40+ | J34: =IF(V34>1000,_xlfn.CONCAT(TEXT(V34/1000,"$#.0"),"T"),_xlfn.CONCAT(TEXT(V34,"$#"),"B")) -> $408B | K34: =_xlfn.CONCAT(TEXT(SUMIFS(raw_output!$N$2:$N$197,raw_output!$M$2:$M$197,'Overall Output. Labeled'!$N34,raw_output!$A$2:$A$197,'Overall Output. Labeled'!$U34,raw_output!$B$2:$B$197,'Overall Output. Labeled'!$S34,raw_output!$C$2:$C$197,'Overall Output. Labeled'!$T34,raw_output!$D$2:$D$197,'Overall Output. Labeled'!$P34,raw_output!$E$2:$E$197,'Overall Output. Labeled'!$Q34,raw_output!$F$2:$F$197,'Overall Output. Labeled'!$R34),"$#.0"),"T") -> $5.0T | L34: =IF(W34>1000,_xlfn.CONCAT(TEXT(W34/1000,"#.#"),"M"),_xlfn.CONCAT(TEXT(W34,"#"),"k")) -> 1.7M | M34: =TEXT(SUMIFS(raw_output!$L$2:$L$197,raw_output!$M$2:$M$197,'Overall Output. Labeled'!$N34,raw_output!$A$2:$A$197,'Overall Output. Labeled'!$U34,raw_output!$B$2:$B$197,'Overall Output. Labeled'!$S34,raw_output!$C$2:$C$197,'Overall Output. Labeled'!$T34,raw_output!$D$2:$D$197,'Overall Output. Labeled'!$P34,raw_output!$E$2:$E$197,'Overall Output. Labeled'!$Q34,raw_output!$F$2:$F$197,'Overall Output. Labeled'!$R34),"$#.##") -> $425.39 | N34: 0.05 | O34: 0.5 | P34: =F34*$O34 -> 0.5 | Q34: =G34*$O34 -> 0.5 | R34: =H34*$O34 -> 0.5 | S34: 10 | T34: 20 | U34: 40 | V34: =SUMIFS(raw_output!$K$2:$K$197,raw_output!$A$2:$A$197,'Overall Output. Labeled'!$U34,raw_output!$B$2:$B$197,'Overall Output. Labeled'!$S34,raw_output!$C$2:$C$197,'Overall Output. Labeled'!$T34,raw_output!$D$2:$D$197,'Overall Output. Labeled'!$P34,raw_output!$E$2:$E$197,'Overall Output. Labeled'!$Q34,raw_output!$F$2:$F$197,'Overall Output. Labeled'!$R34,raw_output!$M$2:$M$197,'Overall Output. Labeled'!$N34) -> 408.38262 | W34: {=SUMIFS(raw_output!$J$2:$J$197,raw_output!$M$2:$M$197,'Overall Output. Labeled'!$N34,raw_output!$A$2:$A$197,'Overall Output. Labeled'!$U34,raw_output!$B$2:$B$197,'Overall Output. Labeled'!$S34,raw_output!$C$2:$C$197,'Overall Output. Labeled'!$T34,raw_output!$D$2:$D$197,'Overall Output. Labeled'!$P34,raw_output!$E$2:$E$197,'Overall Output. Labeled'!$Q34,raw_output!$F$2:$F$197,'Overall Output. Labeled'!$R34)*1000} -> 1723.1995
A39: NOTES:
A40: Results from source other than OG-USA simulation
A41: Computed from other sims
A42: From Simulation Tool (not direct OG-USA simulation)
A43: Not current in book, but discussion about including
C45: Hard coded values
A49: Nature Aging, Online Methods | C49: 41 is the new 40, 1% discount | F49: 1 | G49: 1 | H49: 1 | I49: =CONCATENATE(U49,"+") -> 40+ | J49: =IF(V49>1000,_xlfn.CONCAT(TEXT(V49/1000,"$#.0"),"T"),_xlfn.CONCAT(TEXT(V49,"$#"),"B")) -> $408B | K49: =_xlfn.CONCAT(TEXT(SUMIFS(raw_output!$N$2:$N$197,raw_output!$M$2:$M$197,'Overall Output. Labeled'!$N49,raw_output!$A$2:$A$197,'Overall Output. Labeled'!$U49,raw_output!$B$2:$B$197,'Overall Output. Labeled'!$S49,raw_output!$C$2:$C$197,'Overall Output. Labeled'!$T49,raw_output!$D$2:$D$197,'Overall Output. Labeled'!$P49,raw_output!$E$2:$E$197,'Overall Output. Labeled'!$Q49,raw_output!$F$2:$F$197,'Overall Output. Labeled'!$R49),"$#.0"),"T") -> $53.3T | L49: =IF(W49>1000,_xlfn.CONCAT(TEXT(W49/1000,"#.#"),"M"),_xlfn.CONCAT(TEXT(W49,"#"),"k")) -> 1.7M | M49: =TEXT(SUMIFS(raw_output!$L$2:$L$197,raw_output!$M$2:$M$197,'Overall Output. Labeled'!$N49,raw_output!$A$2:$A$197,'Overall Output. Labeled'!$U49,raw_output!$B$2:$B$197,'Overall Output. Labeled'!$S49,raw_output!$C$2:$C$197,'Overall Output. Labeled'!$T49,raw_output!$D$2:$D$197,'Overall Output. Labeled'!$P49,raw_output!$E$2:$E$197,'Overall Output. Labeled'!$Q49,raw_output!$F$2:$F$197,'Overall Output. Labeled'!$R49),"$#.##") -> $425.39 | N49: 0.01 | O49: 0.5 | P49: =F49*$O49 -> 0.5 | Q49: =G49*$O49 -> 0.5 | R49: =H49*$O49 -> 0.5 | S49: 10 | T49: 20 | U49: 40 | V49: =SUMIFS(raw_output!$K$2:$K$197,raw_output!$M$2:$M$197,'Overall Output. Labeled'!$N49,raw_output!$A$2:$A$197,'Overall Output. Labeled'!$U49,raw_output!$B$2:$B$197,'Overall Output. Labeled'!$S49,raw_output!$C$2:$C$197,'Overall Output. Labeled'!$T49,raw_output!$D$2:$D$197,'Overall Output. Labeled'!$P49,raw_output!$E$2:$E$197,'Overall Output. Labeled'!$Q49,raw_output!$F$2:$F$197,'Overall Output. Labeled'!$R49) -> 408.38262 | W49: {=SUMIFS(raw_output!$J$2:$J$197,raw_output!$M$2:$M$197,'Overall Output. Labeled'!$N49,raw_output!$A$2:$A$197,'Overall Output. Labeled'!$U49,raw_output!$B$2:$B$197,'Overall Output. Labeled'!$S49,raw_output!$C$2:$C$197,'Overall Output. Labeled'!$T49,raw_output!$D$2:$D$197,'Overall Output. Labeled'!$P49,raw_output!$E$2:$E$197,'Overall Output. Labeled'!$Q49,raw_output!$F$2:$F$197,'Overall Output. Labeled'!$R49)*1000} -> 1723.1995
A50: Nature Aging, Online Methods | C50: 41 is the new 40, 2% discount | F50: 1 | G50: 1 | H50: 1 | I50: =CONCATENATE(U50,"+") -> 40+ | J50: =IF(V50>1000,_xlfn.CONCAT(TEXT(V50/1000,"$#.0"),"T"),_xlfn.CONCAT(TEXT(V50,"$#"),"B")) -> $408B | K50: =_xlfn.CONCAT(TEXT(SUMIFS(raw_output!$N$2:$N$197,raw_output!$M$2:$M$197,'Overall Output. Labeled'!$N50,raw_output!$A$2:$A$197,'Overall Output. Labeled'!$U50,raw_output!$B$2:$B$197,'Overall Output. Labeled'!$S50,raw_output!$C$2:$C$197,'Overall Output. Labeled'!$T50,raw_output!$D$2:$D$197,'Overall Output. Labeled'!$P50,raw_output!$E$2:$E$197,'Overall Output. Labeled'!$Q50,raw_output!$F$2:$F$197,'Overall Output. Labeled'!$R50),"$#.0"),"T") -> $27.1T | L50: =IF(W50>1000,_xlfn.CONCAT(TEXT(W50/1000,"#.#"),"M"),_xlfn.CONCAT(TEXT(W50,"#"),"k")) -> 1.7M | M50: =TEXT(SUMIFS(raw_output!$L$2:$L$197,raw_output!$M$2:$M$197,'Overall Output. Labeled'!$N50,raw_output!$A$2:$A$197,'Overall Output. Labeled'!$U50,raw_output!$B$2:$B$197,'Overall Output. Labeled'!$S50,raw_output!$C$2:$C$197,'Overall Output. Labeled'!$T50,raw_output!$D$2:$D$197,'Overall Output. Labeled'!$P50,raw_output!$E$2:$E$197,'Overall Output. Labeled'!$Q50,raw_output!$F$2:$F$197,'Overall Output. Labeled'!$R50),"$#.##") -> $425.39 | N50: 0.02 | O50: 0.5 | P50: =F50*$O50 -> 0.5 | Q50: =G50*$O50 -> 0.5 | R50: =H50*$O50 -> 0.5 | S50: 10 | T50: 20 | U50: 40 | V50: =SUMIFS(raw_output!$K$2:$K$197,raw_output!$M$2:$M$197,'Overall Output. Labeled'!$N50,raw_output!$A$2:$A$197,'Overall Output. Labeled'!$U50,raw_output!$B$2:$B$197,'Overall Output. Labeled'!$S50,raw_output!$C$2:$C$197,'Overall Output. Labeled'!$T50,raw_output!$D$2:$D$197,'Overall Output. Labeled'!$P50,raw_output!$E$2:$E$197,'Overall Output. Labeled'!$Q50,raw_output!$F$2:$F$197,'Overall Output. Labeled'!$R50) -> 408.38262 | W50: {=SUMIFS(raw_output!$J$2:$J$197,raw_output!$M$2:$M$197,'Overall Output. Labeled'!$N50,raw_output!$A$2:$A$197,'Overall Output. Labeled'!$U50,raw_output!$B$2:$B$197,'Overall Output. Labeled'!$S50,raw_output!$C$2:$C$197,'Overall Output. Labeled'!$T50,raw_output!$D$2:$D$197,'Overall Output. Labeled'!$P50,raw_output!$E$2:$E$197,'Overall Output. Labeled'!$Q50,raw_output!$F$2:$F$197,'Overall Output. Labeled'!$R50)*1000} -> 1723.1995
A51: Nature Aging, Online Methods | C51: 41 is the new 40, 3% discount | F51: 1 | G51: 1 | H51: 1 | I51: =CONCATENATE(U51,"+") -> 40+ | J51: =IF(V51>1000,_xlfn.CONCAT(TEXT(V51/1000,"$#.0"),"T"),_xlfn.CONCAT(TEXT(V51,"$#"),"B")) -> $408B | K51: =_xlfn.CONCAT(TEXT(SUMIFS(raw_output!$N$2:$N$197,raw_output!$M$2:$M$197,'Overall Output. Labeled'!$N51,raw_output!$A$2:$A$197,'Overall Output. Labeled'!$U51,raw_output!$B$2:$B$197,'Overall Output. Labeled'!$S51,raw_output!$C$2:$C$197,'Overall Output. Labeled'!$T51,raw_output!$D$2:$D$197,'Overall Output. Labeled'!$P51,raw_output!$E$2:$E$197,'Overall Output. Labeled'!$Q51,raw_output!$F$2:$F$197,'Overall Output. Labeled'!$R51),"$#.0"),"T") -> $14.6T | L51: =IF(W51>1000,_xlfn.CONCAT(TEXT(W51/1000,"#.#"),"M"),_xlfn.CONCAT(TEXT(W51,"#"),"k")) -> 1.7M | M51: =TEXT(SUMIFS(raw_output!$L$2:$L$197,raw_output!$M$2:$M$197,'Overall Output. Labeled'!$N51,raw_output!$A$2:$A$197,'Overall Output. Labeled'!$U51,raw_output!$B$2:$B$197,'Overall Output. Labeled'!$S51,raw_output!$C$2:$C$197,'Overall Output. Labeled'!$T51,raw_output!$D$2:$D$197,'Overall Output. Labeled'!$P51,raw_output!$E$2:$E$197,'Overall Output. Labeled'!$Q51,raw_output!$F$2:$F$197,'Overall Output. Labeled'!$R51),"$#.##") -> $425.39 | N51: 0.03 | O51: 0.5 | P51: =F51*$O51 -> 0.5 | Q51: =G51*$O51 -> 0.5 | R51: =H51*$O51 -> 0.5 | S51: 10 | T51: 20 | U51: 40 | V51: =SUMIFS(raw_output!$K$2:$K$197,raw_output!$M$2:$M$197,'Overall Output. Labeled'!$N51,raw_output!$A$2:$A$197,'Overall Output. Labeled'!$U51,raw_output!$B$2:$B$197,'Overall Output. Labeled'!$S51,raw_output!$C$2:$C$197,'Overall Output. Labeled'!$T51,raw_output!$D$2:$D$197,'Overall Output. Labeled'!$P51,raw_output!$E$2:$E$197,'Overall Output. Labeled'!$Q51,raw_output!$F$2:$F$197,'Overall Output. Labeled'!$R51) -> 408.38262 | W51: {=SUMIFS(raw_output!$J$2:$J$197,raw_output!$M$2:$M$197,'Overall Output. Labeled'!$N51,raw_output!$A$2:$A$197,'Overall Output. Labeled'!$U51,raw_output!$B$2:$B$197,'Overall Output. Labeled'!$S51,raw_output!$C$2:$C$197,'Overall Output. Labeled'!$T51,raw_output!$D$2:$D$197,'Overall Output. Labeled'!$P51,raw_output!$E$2:$E$197,'Overall Output. Labeled'!$Q51,raw_output!$F$2:$F$197,'Overall Output. Labeled'!$R51)*1000} -> 1723.1995
A52: Nature Aging, Online Methods | C52: 41 is the new 40, 4% discount | F52: 1 | G52: 1 | H52: 1 | I52: =CONCATENATE(U52,"+") -> 40+ | J52: =IF(V52>1000,_xlfn.CONCAT(TEXT(V52/1000,"$#.0"),"T"),_xlfn.CONCAT(TEXT(V52,"$#"),"B")) -> $408B | K52: =_xlfn.CONCAT(TEXT(SUMIFS(raw_output!$N$2:$N$197,raw_output!$M$2:$M$197,'Overall Output. Labeled'!$N52,raw_output!$A$2:$A$197,'Overall Output. Labeled'!$U52,raw_output!$B$2:$B$197,'Overall Output. Labeled'!$S52,raw_output!$C$2:$C$197,'Overall Output. Labeled'!$T52,raw_output!$D$2:$D$197,'Overall Output. Labeled'!$P52,raw_output!$E$2:$E$197,'Overall Output. Labeled'!$Q52,raw_output!$F$2:$F$197,'Overall Output. Labeled'!$R52),"$#.0"),"T") -> $8.3T | L52: =IF(W52>1000,_xlfn.CONCAT(TEXT(W52/1000,"#.#"),"M"),_xlfn.CONCAT(TEXT(W52,"#"),"k")) -> 1.7M | M52: =TEXT(SUMIFS(raw_output!$L$2:$L$197,raw_output!$M$2:$M$197,'Overall Output. Labeled'!$N52,raw_output!$A$2:$A$197,'Overall Output. Labeled'!$U52,raw_output!$B$2:$B$197,'Overall Output. Labeled'!$S52,raw_output!$C$2:$C$197,'Overall Output. Labeled'!$T52,raw_output!$D$2:$D$197,'Overall Output. Labeled'!$P52,raw_output!$E$2:$E$197,'Overall Output. Labeled'!$Q52,raw_output!$F$2:$F$197,'Overall Output. Labeled'!$R52),"$#.##") -> $425.39 | N52: 0.04 | O52: 0.5 | P52: =F52*$O52 -> 0.5 | Q52: =G52*$O52 -> 0.5 | R52: =H52*$O52 -> 0.5 | S52: 10 | T52: 20 | U52: 40 | V52: =SUMIFS(raw_output!$K$2:$K$197,raw_output!$M$2:$M$197,'Overall Output. Labeled'!$N52,raw_output!$A$2:$A$197,'Overall Output. Labeled'!$U52,raw_output!$B$2:$B$197,'Overall Output. Labeled'!$S52,raw_output!$C$2:$C$197,'Overall Output. Labeled'!$T52,raw_output!$D$2:$D$197,'Overall Output. Labeled'!$P52,raw_output!$E$2:$E$197,'Overall Output. Labeled'!$Q52,raw_output!$F$2:$F$197,'Overall Output. Labeled'!$R52) -> 408.38262 | W52: {=SUMIFS(raw_output!$J$2:$J$197,raw_output!$M$2:$M$197,'Overall Output. Labeled'!$N52,raw_output!$A$2:$A$197,'Overall Output. Labeled'!$U52,raw_output!$B$2:$B$197,'Overall Output. Labeled'!$S52,raw_output!$C$2:$C$197,'Overall Output. Labeled'!$T52,raw_output!$D$2:$D$197,'Overall Output. Labeled'!$P52,raw_output!$E$2:$E$197,'Overall Output. Labeled'!$Q52,raw_output!$F$2:$F$197,'Overall Output. Labeled'!$R52)*1000} -> 1723.1995
A53: Nature Aging, Online Methods | C53: Slow brain aging, 1% discount | F53: 0.2 | G53: 0.7 | H53: 0 | I53: =CONCATENATE(U53,"+") -> 40+ | J53: =IF(V53>1000,_xlfn.CONCAT(TEXT(V53/1000,"$#.0"),"T"),_xlfn.CONCAT(TEXT(V53,"$#"),"B")) -> $201B | K53: =_xlfn.CONCAT(TEXT(SUMIFS(raw_output!$N$2:$N$197,raw_output!$M$2:$M$197,'Overall Output. Labeled'!$N53,raw_output!$A$2:$A$197,'Overall Output. Labeled'!$U53,raw_output!$B$2:$B$197,'Overall Output. Labeled'!$S53,raw_output!$C$2:$C$197,'Overall Output. Labeled'!$T53,raw_output!$D$2:$D$197,'Overall Output. Labeled'!$P53,raw_output!$E$2:$E$197,'Overall Output. Labeled'!$Q53,raw_output!$F$2:$F$197,'Overall Output. Labeled'!$R53),"$#.0"),"T") -> $16.1T | L53: =IF(W53>1000,_xlfn.CONCAT(TEXT(W53/1000,"#.#"),"M"),_xlfn.CONCAT(TEXT(W53,"#"),"k")) -> 268k | M53: =TEXT(SUMIFS(raw_output!$L$2:$L$197,raw_output!$M$2:$M$197,'Overall Output. Labeled'!$N53,raw_output!$A$2:$A$197,'Overall Output. Labeled'!$U53,raw_output!$B$2:$B$197,'Overall Output. Labeled'!$S53,raw_output!$C$2:$C$197,'Overall Output. Labeled'!$T53,raw_output!$D$2:$D$197,'Overall Output. Labeled'!$P53,raw_output!$E$2:$E$197,'Overall Output. Labeled'!$Q53,raw_output!$F$2:$F$197,'Overall Output. Labeled'!$R53),"$#.##") -> $507.82 | N53: 0.01 | O53: 0.5 | P53: =F53*$O53 -> 0.1 | Q53: =G53*$O53 -> 0.35 | R53: =H53*$O53 -> 0 | S53: 10 | T53: 20 | U53: 40 | V53: =SUMIFS(raw_output!$K$2:$K$197,raw_output!$M$2:$M$197,'Overall Output. Labeled'!$N53,raw_output!$A$2:$A$197,'Overall Output. Labeled'!$U53,raw_output!$B$2:$B$197,'Overall Output. Labeled'!$S53,raw_output!$C$2:$C$197,'Overall Output. Labeled'!$T53,raw_output!$D$2:$D$197,'Overall Output. Labeled'!$P53,raw_output!$E$2:$E$197,'Overall Output. Labeled'!$Q53,raw_output!$F$2:$F$197,'Overall Output. Labeled'!$R53) -> 201.2899 | W53: {=SUMIFS(raw_output!$J$2:$J$197,raw_output!$M$2:$M$197,'Overall Output. Labeled'!$N53,raw_output!$A$2:$A$197,'Overall Output. Labeled'!$U53,raw_output!$B$2:$B$197,'Overall Output. Labeled'!$S53,raw_output!$C$2:$C$197,'Overall Output. Labeled'!$T53,raw_output!$D$2:$D$197,'Overall Output. Labeled'!$P53,raw_output!$E$2:$E$197,'Overall Output. Labeled'!$Q53,raw_output!$F$2:$F$197,'Overall Output. Labeled'!$R53)*1000} -> 268.1277
A54: Nature Aging, Online Methods | C54: Slow brain aging, 2% discount | F54: 0.2 | G54: 0.7 | H54: 0 | I54: =CONCATENATE(U54,"+") -> 40+ | J54: =IF(V54>1000,_xlfn.CONCAT(TEXT(V54/1000,"$#.0"),"T"),_xlfn.CONCAT(TEXT(V54,"$#"),"B")) -> $201B | K54: =_xlfn.CONCAT(TEXT(SUMIFS(raw_output!$N$2:$N$197,raw_output!$M$2:$M$197,'Overall Output. Labeled'!$N54,raw_output!$A$2:$A$197,'Overall Output. Labeled'!$U54,raw_output!$B$2:$B$197,'Overall Output. Labeled'!$S54,raw_output!$C$2:$C$197,'Overall Output. Labeled'!$T54,raw_output!$D$2:$D$197,'Overall Output. Labeled'!$P54,raw_output!$E$2:$E$197,'Overall Output. Labeled'!$Q54,raw_output!$F$2:$F$197,'Overall Output. Labeled'!$R54),"$#.0"),"T") -> $8.9T | L54: =IF(W54>1000,_xlfn.CONCAT(TEXT(W54/1000,"#.#"),"M"),_xlfn.CONCAT(TEXT(W54,"#"),"k")) -> 268k | M54: =TEXT(SUMIFS(raw_output!$L$2:$L$197,raw_output!$M$2:$M$197,'Overall Output. Labeled'!$N54,raw_output!$A$2:$A$197,'Overall Output. Labeled'!$U54,raw_output!$B$2:$B$197,'Overall Output. Labeled'!$S54,raw_output!$C$2:$C$197,'Overall Output. Labeled'!$T54,raw_output!$D$2:$D$197,'Overall Output. Labeled'!$P54,raw_output!$E$2:$E$197,'Overall Output. Labeled'!$Q54,raw_output!$F$2:$F$197,'Overall Output. Labeled'!$R54),"$#.##") -> $507.82 | N54: 0.02 | O54: 0.5 | P54: =F54*$O54 -> 0.1 | Q54: =G54*$O54 -> 0.35 | R54: =H54*$O54 -> 0 | S54: 10 | T54: 20 | U54: 40 | V54: =SUMIFS(raw_output!$K$2:$K$197,raw_output!$M$2:$M$197,'Overall Output. Labeled'!$N54,raw_output!$A$2:$A$197,'Overall Output. Labeled'!$U54,raw_output!$B$2:$B$197,'Overall Output. Labeled'!$S54,raw_output!$C$2:$C$197,'Overall Output. Labeled'!$T54,raw_output!$D$2:$D$197,'Overall Output. Labeled'!$P54,raw_output!$E$2:$E$197,'Overall Output. Labeled'!$Q54,raw_output!$F$2:$F$197,'Overall Output. Labeled'!$R54) -> 201.2899 | W54: {=SUMIFS(raw_output!$J$2:$J$197,raw_output!$M$2:$M$197,'Overall Output. Labeled'!$N54,raw_output!$A$2:$A$197,'Overall Output. Labeled'!$U54,raw_output!$B$2:$B$197,'Overall Output. Labeled'!$S54,raw_output!$C$2:$C$197,'Overall Output. Labeled'!$T54,raw_output!$D$2:$D$197,'Overall Output. Labeled'!$P54,raw_output!$E$2:$E$197,'Overall Output. Labeled'!$Q54,raw_output!$F$2:$F$197,'Overall Output. Labeled'!$R54)*1000} -> 268.1277
A55: Nature Aging, Online Methods | C55: Slow brain aging, 3% discount | F55: 0.2 | G55: 0.7 | H55: 0 | I55: =CONCATENATE(U55,"+") -> 40+ | J55: =IF(V55>1000,_xlfn.CONCAT(TEXT(V55/1000,"$#.0"),"T"),_xlfn.CONCAT(TEXT(V55,"$#"),"B")) -> $201B | K55: =_xlfn.CONCAT(TEXT(SUMIFS(raw_output!$N$2:$N$197,raw_output!$M$2:$M$197,'Overall Output. Labeled'!$N55,raw_output!$A$2:$A$197,'Overall Output. Labeled'!$U55,raw_output!$B$2:$B$197,'Overall Output. Labeled'!$S55,raw_output!$C$2:$C$197,'Overall Output. Labeled'!$T55,raw_output!$D$2:$D$197,'Overall Output. Labeled'!$P55,raw_output!$E$2:$E$197,'Overall Output. Labeled'!$Q55,raw_output!$F$2:$F$197,'Overall Output. Labeled'!$R55),"$#.0"),"T") -> $5.2T | L55: =IF(W55>1000,_xlfn.CONCAT(TEXT(W55/1000,"#.#"),"M"),_xlfn.CONCAT(TEXT(W55,"#"),"k")) -> 268k | M55: =TEXT(SUMIFS(raw_output!$L$2:$L$197,raw_output!$M$2:$M$197,'Overall Output. Labeled'!$N55,raw_output!$A$2:$A$197,'Overall Output. Labeled'!$U55,raw_output!$B$2:$B$197,'Overall Output. Labeled'!$S55,raw_output!$C$2:$C$197,'Overall Output. Labeled'!$T55,raw_output!$D$2:$D$197,'Overall Output. Labeled'!$P55,raw_output!$E$2:$E$197,'Overall Output. Labeled'!$Q55,raw_output!$F$2:$F$197,'Overall Output. Labeled'!$R55),"$#.##") -> $507.82 | N55: 0.03 | O55: 0.5 | P55: =F55*$O55 -> 0.1 | Q55: =G55*$O55 -> 0.35 | R55: =H55*$O55 -> 0 | S55: 10 | T55: 20 | U55: 40 | V55: =SUMIFS(raw_output!$K$2:$K$197,raw_output!$M$2:$M$197,'Overall Output. Labeled'!$N55,raw_output!$A$2:$A$197,'Overall Output. Labeled'!$U55,raw_output!$B$2:$B$197,'Overall Output. Labeled'!$S55,raw_output!$C$2:$C$197,'Overall Output. Labeled'!$T55,raw_output!$D$2:$D$197,'Overall Output. Labeled'!$P55,raw_output!$E$2:$E$197,'Overall Output. Labeled'!$Q55,raw_output!$F$2:$F$197,'Overall Output. Labeled'!$R55) -> 201.2899 | W55: {=SUMIFS(raw_output!$J$2:$J$197,raw_output!$M$2:$M$197,'Overall Output. Labeled'!$N55,raw_output!$A$2:$A$197,'Overall Output. Labeled'!$U55,raw_output!$B$2:$B$197,'Overall Output. Labeled'!$S55,raw_output!$C$2:$C$197,'Overall Output. Labeled'!$T55,raw_output!$D$2:$D$197,'Overall Output. Labeled'!$P55,raw_output!$E$2:$E$197,'Overall Output. Labeled'!$Q55,raw_output!$F$2:$F$197,'Overall Output. Labeled'!$R55)*1000} -> 268.1277
A56: Nature Aging, Online Methods | C56: Slow brain aging, 4% discount | F56: 0.2 | G56: 0.7 | H56: 0 | I56: =CONCATENATE(U56,"+") -> 40+ | J56: =IF(V56>1000,_xlfn.CONCAT(TEXT(V56/1000,"$#.0"),"T"),_xlfn.CONCAT(TEXT(V56,"$#"),"B")) -> $201B | K56: =_xlfn.CONCAT(TEXT(SUMIFS(raw_output!$N$2:$N$197,raw_output!$M$2:$M$197,'Overall Output. Labeled'!$N56,raw_output!$A$2:$A$197,'Overall Output. Labeled'!$U56,raw_output!$B$2:$B$197,'Overall Output. Labeled'!$S56,raw_output!$C$2:$C$197,'Overall Output. Labeled'!$T56,raw_output!$D$2:$D$197,'Overall Output. Labeled'!$P56,raw_output!$E$2:$E$197,'Overall Output. Labeled'!$Q56,raw_output!$F$2:$F$197,'Overall Output. Labeled'!$R56),"$#.0"),"T") -> $3.2T | L56: =IF(W56>1000,_xlfn.CONCAT(TEXT(W56/1000,"#.#"),"M"),_xlfn.CONCAT(TEXT(W56,"#"),"k")) -> 268k | M56: =TEXT(SUMIFS(raw_output!$L$2:$L$197,raw_output!$M$2:$M$197,'Overall Output. Labeled'!$N56,raw_output!$A$2:$A$197,'Overall Output. Labeled'!$U56,raw_output!$B$2:$B$197,'Overall Output. Labeled'!$S56,raw_output!$C$2:$C$197,'Overall Output. Labeled'!$T56,raw_output!$D$2:$D$197,'Overall Output. Labeled'!$P56,raw_output!$E$2:$E$197,'Overall Output. Labeled'!$Q56,raw_output!$F$2:$F$197,'Overall Output. Labeled'!$R56),"$#.##") -> $507.82 | N56: 0.04 | O56: 0.5 | P56: =F56*$O56 -> 0.1 | Q56: =G56*$O56 -> 0.35 | R56: =H56*$O56 -> 0 | S56: 10 | T56: 20 | U56: 40 | V56: =SUMIFS(raw_output!$K$2:$K$197,raw_output!$M$2:$M$197,'Overall Output. Labeled'!$N56,raw_output!$A$2:$A$197,'Overall Output. Labeled'!$U56,raw_output!$B$2:$B$197,'Overall Output. Labeled'!$S56,raw_output!$C$2:$C$197,'Overall Output. Labeled'!$T56,raw_output!$D$2:$D$197,'Overall Output. Labeled'!$P56,raw_output!$E$2:$E$197,'Overall Output. Labeled'!$Q56,raw_output!$F$2:$F$197,'Overall Output. Labeled'!$R56) -> 201.2899 | W56: {=SUMIFS(raw_output!$J$2:$J$197,raw_output!$M$2:$M$197,'Overall Output. Labeled'!$N56,raw_output!$A$2:$A$197,'Overall Output. Labeled'!$U56,raw_output!$B$2:$B$197,'Overall Output. Labeled'!$S56,raw_output!$C$2:$C$197,'Overall Output. Labeled'!$T56,raw_output!$D$2:$D$197,'Overall Output. Labeled'!$P56,raw_output!$E$2:$E$197,'Overall Output. Labeled'!$Q56,raw_output!$F$2:$F$197,'Overall Output. Labeled'!$R56)*1000} -> 268.1277
A57: Nature Aging, Online Methods | C57: Slow reproductive aging, 1% discount | F57: 0.02 | G57: 0.04 | H57: 1 | I57: =CONCATENATE(U57,"+") -> 40+ | J57: =IF(V57>1000,_xlfn.CONCAT(TEXT(V57/1000,"$#.0"),"T"),_xlfn.CONCAT(TEXT(V57,"$#"),"B")) -> -$7B | K57: =_xlfn.CONCAT(TEXT(SUMIFS(raw_output!$N$2:$N$197,raw_output!$M$2:$M$197,'Overall Output. Labeled'!$N57,raw_output!$A$2:$A$197,'Overall Output. Labeled'!$U57,raw_output!$B$2:$B$197,'Overall Output. Labeled'!$S57,raw_output!$C$2:$C$197,'Overall Output. Labeled'!$T57,raw_output!$D$2:$D$197,'Overall Output. Labeled'!$P57,raw_output!$E$2:$E$197,'Overall Output. Labeled'!$Q57,raw_output!$F$2:$F$197,'Overall Output. Labeled'!$R57),"$#.0"),"T") -> $19.5T | L57: =IF(W57>1000,_xlfn.CONCAT(TEXT(W57/1000,"#.#"),"M"),_xlfn.CONCAT(TEXT(W57,"#"),"k")) -> 391k | M57: =TEXT(SUMIFS(raw_output!$L$2:$L$197,raw_output!$M$2:$M$197,'Overall Output. Labeled'!$N57,raw_output!$A$2:$A$197,'Overall Output. Labeled'!$U57,raw_output!$B$2:$B$197,'Overall Output. Labeled'!$S57,raw_output!$C$2:$C$197,'Overall Output. Labeled'!$T57,raw_output!$D$2:$D$197,'Overall Output. Labeled'!$P57,raw_output!$E$2:$E$197,'Overall Output. Labeled'!$Q57,raw_output!$F$2:$F$197,'Overall Output. Labeled'!$R57),"$#.##") -> -$60.7 | N57: 0.01 | O57: 0.5 | P57: =F57*$O57 -> 0.01 | Q57: =G57*$O57 -> 0.02 | R57: =H57*$O57 -> 0.5 | S57: 10 | T57: 20 | U57: 40 | V57: =SUMIFS(raw_output!$K$2:$K$197,raw_output!$M$2:$M$197,'Overall Output. Labeled'!$N57,raw_output!$A$2:$A$197,'Overall Output. Labeled'!$U57,raw_output!$B$2:$B$197,'Overall Output. Labeled'!$S57,raw_output!$C$2:$C$197,'Overall Output. Labeled'!$T57,raw_output!$D$2:$D$197,'Overall Output. Labeled'!$P57,raw_output!$E$2:$E$197,'Overall Output. Labeled'!$Q57,raw_output!$F$2:$F$197,'Overall Output. Labeled'!$R57) -> -6.9483302 | W57: {=SUMIFS(raw_output!$J$2:$J$197,raw_output!$M$2:$M$197,'Overall Output. Labeled'!$N57,raw_output!$A$2:$A$197,'Overall Output. Labeled'!$U57,raw_output!$B$2:$B$197,'Overall Output. Labeled'!$S57,raw_output!$C$2:$C$197,'Overall Output. Labeled'!$T57,raw_output!$D$2:$D$197,'Overall Output. Labeled'!$P57,raw_output!$E$2:$E$197,'Overall Output. Labeled'!$Q57,raw_output!$F$2:$F$197,'Overall Output. Labeled'!$R57)*1000} -> 391.36761
A58: Nature Aging, Online Methods | C58: Slow reproductive aging, 2% discount | F58: 0.02 | G58: 0.04 | H58: 1 | I58: =CONCATENATE(U58,"+") -> 40+ | J58: =IF(V58>1000,_xlfn.CONCAT(TEXT(V58/1000,"$#.0"),"T"),_xlfn.CONCAT(TEXT(V58,"$#"),"B")) -> -$7B | K58: =_xlfn.CONCAT(TEXT(SUMIFS(raw_output!$N$2:$N$197,raw_output!$M$2:$M$197,'Overall Output. Labeled'!$N58,raw_output!$A$2:$A$197,'Overall Output. Labeled'!$U58,raw_output!$B$2:$B$197,'Overall Output. Labeled'!$S58,raw_output!$C$2:$C$197,'Overall Output. Labeled'!$T58,raw_output!$D$2:$D$197,'Overall Output. Labeled'!$P58,raw_output!$E$2:$E$197,'Overall Output. Labeled'!$Q58,raw_output!$F$2:$F$197,'Overall Output. Labeled'!$R58),"$#.0"),"T") -> $8.6T | L58: =IF(W58>1000,_xlfn.CONCAT(TEXT(W58/1000,"#.#"),"M"),_xlfn.CONCAT(TEXT(W58,"#"),"k")) -> 391k | M58: =TEXT(SUMIFS(raw_output!$L$2:$L$197,raw_output!$M$2:$M$197,'Overall Output. Labeled'!$N58,raw_output!$A$2:$A$197,'Overall Output. Labeled'!$U58,raw_output!$B$2:$B$197,'Overall Output. Labeled'!$S58,raw_output!$C$2:$C$197,'Overall Output. Labeled'!$T58,raw_output!$D$2:$D$197,'Overall Output. Labeled'!$P58,raw_output!$E$2:$E$197,'Overall Output. Labeled'!$Q58,raw_output!$F$2:$F$197,'Overall Output. Labeled'!$R58),"$#.##") -> -$60.7 | N58: 0.02 | O58: 0.5 | P58: =F58*$O58 -> 0.01 | Q58: =G58*$O58 -> 0.02 | R58: =H58*$O58 -> 0.5 | S58: 10 | T58: 20 | U58: 40 | V58: =SUMIFS(raw_output!$K$2:$K$197,raw_output!$M$2:$M$197,'Overall Output. Labeled'!$N58,raw_output!$A$2:$A$197,'Overall Output. Labeled'!$U58,raw_output!$B$2:$B$197,'Overall Output. Labeled'!$S58,raw_output!$C$2:$C$197,'Overall Output. Labeled'!$T58,raw_output!$D$2:$D$197,'Overall Output. Labeled'!$P58,raw_output!$E$2:$E$197,'Overall Output. Labeled'!$Q58,raw_output!$F$2:$F$197,'Overall Output. Labeled'!$R58) -> -6.9483302 | W58: {=SUMIFS(raw_output!$J$2:$J$197,raw_output!$M$2:$M$197,'Overall Output. Labeled'!$N58,raw_output!$A$2:$A$197,'Overall Output. Labeled'!$U58,raw_output!$B$2:$B$197,'Overall Output. Labeled'!$S58,raw_output!$C$2:$C$197,'Overall Output. Labeled'!$T58,raw_output!$D$2:$D$197,'Overall Output. Labeled'!$P58,raw_output!$E$2:$E$197,'Overall Output. Labeled'!$Q58,raw_output!$F$2:$F$197,'Overall Output. Labeled'!$R58)*1000} -> 391.36761
A59: Nature Aging, Online Methods | C59: Slow reproductive aging, 3% discount | F59: 0.02 | G59: 0.04 | H59: 1 | I59: =CONCATENATE(U59,"+") -> 40+ | J59: =IF(V59>1000,_xlfn.CONCAT(TEXT(V59/1000,"$#.0"),"T"),_xlfn.CONCAT(TEXT(V59,"$#"),"B")) -> -$7B | K59: =_xlfn.CONCAT(TEXT(SUMIFS(raw_output!$N$2:$N$197,raw_output!$M$2:$M$197,'Overall Output. Labeled'!$N59,raw_output!$A$2:$A$197,'Overall Output. Labeled'!$U59,raw_output!$B$2:$B$197,'Overall Output. Labeled'!$S59,raw_output!$C$2:$C$197,'Overall Output. Labeled'!$T59,raw_output!$D$2:$D$197,'Overall Output. Labeled'!$P59,raw_output!$E$2:$E$197,'Overall Output. Labeled'!$Q59,raw_output!$F$2:$F$197,'Overall Output. Labeled'!$R59),"$#.0"),"T") -> $3.9T | L59: =IF(W59>1000,_xlfn.CONCAT(TEXT(W59/1000,"#.#"),"M"),_xlfn.CONCAT(TEXT(W59,"#"),"k")) -> 391k | M59: =TEXT(SUMIFS(raw_output!$L$2:$L$197,raw_output!$M$2:$M$197,'Overall Output. Labeled'!$N59,raw_output!$A$2:$A$197,'Overall Output. Labeled'!$U59,raw_output!$B$2:$B$197,'Overall Output. Labeled'!$S59,raw_output!$C$2:$C$197,'Overall Output. Labeled'!$T59,raw_output!$D$2:$D$197,'Overall Output. Labeled'!$P59,raw_output!$E$2:$E$197,'Overall Output. Labeled'!$Q59,raw_output!$F$2:$F$197,'Overall Output. Labeled'!$R59),"$#.##") -> -$60.7 | N59: 0.03 | O59: 0.5 | P59: =F59*$O59 -> 0.01 | Q59: =G59*$O59 -> 0.02 | R59: =H59*$O59 -> 0.5 | S59: 10 | T59: 20 | U59: 40 | V59: =SUMIFS(raw_output!$K$2:$K$197,raw_output!$M$2:$M$197,'Overall Output. Labeled'!$N59,raw_output!$A$2:$A$197,'Overall Output. Labeled'!$U59,raw_output!$B$2:$B$197,'Overall Output. Labeled'!$S59,raw_output!$C$2:$C$197,'Overall Output. Labeled'!$T59,raw_output!$D$2:$D$197,'Overall Output. Labeled'!$P59,raw_output!$E$2:$E$197,'Overall Output. Labeled'!$Q59,raw_output!$F$2:$F$197,'Overall Output. Labeled'!$R59) -> -6.9483302 | W59: {=SUMIFS(raw_output!$J$2:$J$197,raw_output!$M$2:$M$197,'Overall Output. Labeled'!$N59,raw_output!$A$2:$A$197,'Overall Output. Labeled'!$U59,raw_output!$B$2:$B$197,'Overall Output. Labeled'!$S59,raw_output!$C$2:$C$197,'Overall Output. Labeled'!$T59,raw_output!$D$2:$D$197,'Overall Output. Labeled'!$P59,raw_output!$E$2:$E$197,'Overall Output. Labeled'!$Q59,raw_output!$F$2:$F$197,'Overall Output. Labeled'!$R59)*1000} -> 391.36761
A60: Nature Aging, Online Methods | C60: Slow reproductive aging, 4% discount | F60: 0.02 | G60: 0.04 | H60: 1 | I60: =CONCATENATE(U60,"+") -> 40+ | J60: =IF(V60>1000,_xlfn.CONCAT(TEXT(V60/1000,"$#.0"),"T"),_xlfn.CONCAT(TEXT(V60,"$#"),"B")) -> -$7B | K60: =_xlfn.CONCAT(TEXT(SUMIFS(raw_output!$N$2:$N$197,raw_output!$M$2:$M$197,'Overall Output. Labeled'!$N60,raw_output!$A$2:$A$197,'Overall Output. Labeled'!$U60,raw_output!$B$2:$B$197,'Overall Output. Labeled'!$S60,raw_output!$C$2:$C$197,'Overall Output. Labeled'!$T60,raw_output!$D$2:$D$197,'Overall Output. Labeled'!$P60,raw_output!$E$2:$E$197,'Overall Output. Labeled'!$Q60,raw_output!$F$2:$F$197,'Overall Output. Labeled'!$R60),"$#.0"),"T") -> $1.8T | L60: =IF(W60>1000,_xlfn.CONCAT(TEXT(W60/1000,"#.#"),"M"),_xlfn.CONCAT(TEXT(W60,"#"),"k")) -> 391k | M60: =TEXT(SUMIFS(raw_output!$L$2:$L$197,raw_output!$M$2:$M$197,'Overall Output. Labeled'!$N60,raw_output!$A$2:$A$197,'Overall Output. Labeled'!$U60,raw_output!$B$2:$B$197,'Overall Output. Labeled'!$S60,raw_output!$C$2:$C$197,'Overall Output. Labeled'!$T60,raw_output!$D$2:$D$197,'Overall Output. Labeled'!$P60,raw_output!$E$2:$E$197,'Overall Output. Labeled'!$Q60,raw_output!$F$2:$F$197,'Overall Output. Labeled'!$R60),"$#.##") -> -$60.7 | N60: 0.04 | O60: 0.5 | P60: =F60*$O60 -> 0.01 | Q60: =G60*$O60 -> 0.02 | R60: =H60*$O60 -> 0.5 | S60: 10 | T60: 20 | U60: 40 | V60: =SUMIFS(raw_output!$K$2:$K$197,raw_output!$M$2:$M$197,'Overall Output. Labeled'!$N60,raw_output!$A$2:$A$197,'Overall Output. Labeled'!$U60,raw_output!$B$2:$B$197,'Overall Output. Labeled'!$S60,raw_output!$C$2:$C$197,'Overall Output. Labeled'!$T60,raw_output!$D$2:$D$197,'Overall Output. Labeled'!$P60,raw_output!$E$2:$E$197,'Overall Output. Labeled'!$Q60,raw_output!$F$2:$F$197,'Overall Output. Labeled'!$R60) -> -6.9483302 | W60: {=SUMIFS(raw_output!$J$2:$J$197,raw_output!$M$2:$M$197,'Overall Output. Labeled'!$N60,raw_output!$A$2:$A$197,'Overall Output. Labeled'!$U60,raw_output!$B$2:$B$197,'Overall Output. Labeled'!$S60,raw_output!$C$2:$C$197,'Overall Output. Labeled'!$T60,raw_output!$D$2:$D$197,'Overall Output. Labeled'!$P60,raw_output!$E$2:$E$197,'Overall Output. Labeled'!$Q60,raw_output!$F$2:$F$197,'Overall Output. Labeled'!$R60)*1000} -> 391.36761
... A64: Nature Aging, Online Methods | C64: 66 is the new 65, 4% discount | F64: 1 | G64: 1 | H64: 1 | I64: =CONCATENATE(U64,"+") -> 65+ | J64: =IF(V64>1000,_xlfn.CONCAT(TEXT(V64/1000,"$#.0"),"T"),_xlfn.CONCAT(TEXT(V64,"$#"),"B")) -> $326B | K64: =_xlfn.CONCAT(TEXT(SUMIFS(raw_output!$N$2:$N$197,raw_output!$M$2:$M$197,'Overall Output. Labeled'!$N64,raw_output!$A$2:$A$197,'Overall Output. Labeled'!$U64,raw_output!$B$2:$B$197,'Overall Output. Labeled'!$S64,raw_output!$C$2:$C$197,'Overall Output. Labeled'!$T64,raw_output!$D$2:$D$197,'Overall Output. Labeled'!$P64,raw_output!$E$2:$E$197,'Overall Output. Labeled'!$Q64,raw_output!$F$2:$F$197,'Overall Output. Labeled'!$R64),"$#.0"),"T") -> $5.2T | L64: =IF(W64>1000,_xlfn.CONCAT(TEXT(W64/1000,"#.#"),"M"),_xlfn.CONCAT(TEXT(W64,"#"),"k")) -> 1.2M | M64: =TEXT(SUMIFS(raw_output!$L$2:$L$197,raw_output!$M$2:$M$197,'Overall Output. Labeled'!$N64,raw_output!$A$2:$A$197,'Overall Output. Labeled'!$U64,raw_output!$B$2:$B$197,'Overall Output. Labeled'!$S64,raw_output!$C$2:$C$197,'Overall Output. Labeled'!$T64,raw_output!$D$2:$D$197,'Overall Output. Labeled'!$P64,raw_output!$E$2:$E$197,'Overall Output. Labeled'!$Q64,raw_output!$F$2:$F$197,'Overall Output. Labeled'!$R64),"$#.##") -> $327.93 | N64: 0.04 | O64: 0.5 | P64: =F64*$O64 -> 0.5 | Q64: =G64*$O64 -> 0.5 | R64: =H64*$O64 -> 0.5 | S64: 10 | T64: 20 | U64: 65 | V64: =SUMIFS(raw_output!$K$2:$K$197,raw_output!$M$2:$M$197,'Overall Output. Labeled'!$N64,raw_output!$A$2:$A$197,'Overall Output. Labeled'!$U64,raw_output!$B$2:$B$197,'Overall Output. Labeled'!$S64,raw_output!$C$2:$C$197,'Overall Output. Labeled'!$T64,raw_output!$D$2:$D$197,'Overall Output. Labeled'!$P64,raw_output!$E$2:$E$197,'Overall Output. Labeled'!$Q64,raw_output!$F$2:$F$197,'Overall Output. Labeled'!$R64) -> 326.36233 | W64: {=SUMIFS(raw_output!$J$2:$J$197,raw_output!$M$2:$M$197,'Overall Output. Labeled'!$N64,raw_output!$A$2:$A$197,'Overall Output. Labeled'!$U64,raw_output!$B$2:$B$197,'Overall Output. Labeled'!$S64,raw_output!$C$2:$C$197,'Overall Output. Labeled'!$T64,raw_output!$D$2:$D$197,'Overall Output. Labeled'!$P64,raw_output!$E$2:$E$197,'Overall Output. Labeled'!$Q64,raw_output!$F$2:$F$197,'Overall Output. Labeled'!$R64)*1000} -> 1178.3827
A65: Nature Aging, Online Methods | C65: 1st gen, 1% | F65: 0.82 | G65: 0.727 | H65: 0 | I65: =CONCATENATE(U65,"+") -> 65+ | J65: =IF(V65>1000,_xlfn.CONCAT(TEXT(V65/1000,"$#.0"),"T"),_xlfn.CONCAT(TEXT(V65,"$#"),"B")) -> $40B | K65: =_xlfn.CONCAT(TEXT(SUMIFS(raw_output!$N$2:$N$197,raw_output!$M$2:$M$197,'Overall Output. Labeled'!$N65,raw_output!$A$2:$A$197,'Overall Output. Labeled'!$U65,raw_output!$B$2:$B$197,'Overall Output. Labeled'!$S65,raw_output!$C$2:$C$197,'Overall Output. Labeled'!$T65,raw_output!$D$2:$D$197,'Overall Output. Labeled'!$P65,raw_output!$E$2:$E$197,'Overall Output. Labeled'!$Q65,raw_output!$F$2:$F$197,'Overall Output. Labeled'!$R65),"$#.0"),"T") -> $4.3T | L65: =IF(W65>1000,_xlfn.CONCAT(TEXT(W65/1000,"#.#"),"M"),_xlfn.CONCAT(TEXT(W65,"#"),"k")) -> 275k | M65: =TEXT(SUMIFS(raw_output!$L$2:$L$197,raw_output!$M$2:$M$197,'Overall Output. Labeled'!$N65,raw_output!$A$2:$A$197,'Overall Output. Labeled'!$U65,raw_output!$B$2:$B$197,'Overall Output. Labeled'!$S65,raw_output!$C$2:$C$197,'Overall Output. Labeled'!$T65,raw_output!$D$2:$D$197,'Overall Output. Labeled'!$P65,raw_output!$E$2:$E$197,'Overall Output. Labeled'!$Q65,raw_output!$F$2:$F$197,'Overall Output. Labeled'!$R65),"$#.##") -> -$19.85 | N65: 0.01 | O65: 0.11 | P65: 0.09 | Q65: 0.08 | R65: =H65*$O65 -> 0 | S65: 5 | T65: 10 | U65: 65 | V65: =SUMIFS(raw_output!$K$2:$K$197,raw_output!$M$2:$M$197,'Overall Output. Labeled'!$N65,raw_output!$A$2:$A$197,'Overall Output. Labeled'!$U65,raw_output!$B$2:$B$197,'Overall Output. Labeled'!$S65,raw_output!$C$2:$C$197,'Overall Output. Labeled'!$T65,raw_output!$D$2:$D$197,'Overall Output. Labeled'!$P65,raw_output!$E$2:$E$197,'Overall Output. Labeled'!$Q65,raw_output!$F$2:$F$197,'Overall Output. Labeled'!$R65) -> 40.442704 | W65: {=SUMIFS(raw_output!$J$2:$J$197,raw_output!$M$2:$M$197,'Overall Output. Labeled'!$N65,raw_output!$A$2:$A$197,'Overall Output. Labeled'!$U65,raw_output!$B$2:$B$197,'Overall Output. Labeled'!$S65,raw_output!$C$2:$C$197,'Overall Output. Labeled'!$T65,raw_output!$D$2:$D$197,'Overall Output. Labeled'!$P65,raw_output!$E$2:$E$197,'Overall Output. Labeled'!$Q65,raw_output!$F$2:$F$197,'Overall Output. Labeled'!$R65)*1000} -> 275.20844
A66: Nature Aging, Online Methods | C66: 1st gen, 2% | F66: 0.82 | G66: 0.727 | H66: 0 | I66: =CONCATENATE(U66,"+") -> 65+ | J66: =IF(V66>1000,_xlfn.CONCAT(TEXT(V66/1000,"$#.0"),"T"),_xlfn.CONCAT(TEXT(V66,"$#"),"B")) -> $40B | K66: =_xlfn.CONCAT(TEXT(SUMIFS(raw_output!$N$2:$N$197,raw_output!$M$2:$M$197,'Overall Output. Labeled'!$N66,raw_output!$A$2:$A$197,'Overall Output. Labeled'!$U66,raw_output!$B$2:$B$197,'Overall Output. Labeled'!$S66,raw_output!$C$2:$C$197,'Overall Output. Labeled'!$T66,raw_output!$D$2:$D$197,'Overall Output. Labeled'!$P66,raw_output!$E$2:$E$197,'Overall Output. Labeled'!$Q66,raw_output!$F$2:$F$197,'Overall Output. Labeled'!$R66),"$#.0"),"T") -> $2.4T | L66: =IF(W66>1000,_xlfn.CONCAT(TEXT(W66/1000,"#.#"),"M"),_xlfn.CONCAT(TEXT(W66,"#"),"k")) -> 275k | M66: =TEXT(SUMIFS(raw_output!$L$2:$L$197,raw_output!$M$2:$M$197,'Overall Output. Labeled'!$N66,raw_output!$A$2:$A$197,'Overall Output. Labeled'!$U66,raw_output!$B$2:$B$197,'Overall Output. Labeled'!$S66,raw_output!$C$2:$C$197,'Overall Output. Labeled'!$T66,raw_output!$D$2:$D$197,'Overall Output. Labeled'!$P66,raw_output!$E$2:$E$197,'Overall Output. Labeled'!$Q66,raw_output!$F$2:$F$197,'Overall Output. Labeled'!$R66),"$#.##") -> -$19.85 | N66: 0.02 | O66: 0.11 | P66: 0.09 | Q66: 0.08 | R66: =H66*$O66 -> 0 | S66: 5 | T66: 10 | U66: 65 | V66: =SUMIFS(raw_output!$K$2:$K$197,raw_output!$M$2:$M$197,'Overall Output. Labeled'!$N66,raw_output!$A$2:$A$197,'Overall Output. Labeled'!$U66,raw_output!$B$2:$B$197,'Overall Output. Labeled'!$S66,raw_output!$C$2:$C$197,'Overall Output. Labeled'!$T66,raw_output!$D$2:$D$197,'Overall Output. Labeled'!$P66,raw_output!$E$2:$E$197,'Overall Output. Labeled'!$Q66,raw_output!$F$2:$F$197,'Overall Output. Labeled'!$R66) -> 40.442704 | W66: {=SUMIFS(raw_output!$J$2:$J$197,raw_output!$M$2:$M$197,'Overall Output. Labeled'!$N66,raw_output!$A$2:$A$197,'Overall Output. Labeled'!$U66,raw_output!$B$2:$B$197,'Overall Output. Labeled'!$S66,raw_output!$C$2:$C$197,'Overall Output. Labeled'!$T66,raw_output!$D$2:$D$197,'Overall Output. Labeled'!$P66,raw_output!$E$2:$E$197,'Overall Output. Labeled'!$Q66,raw_output!$F$2:$F$197,'Overall Output. Labeled'!$R66)*1000} -> 275.20844
A67: Nature Aging, Online Methods | C67: 1st gen, 3% | F67: 0.82 | G67: 0.727 | H67: 0 | I67: =CONCATENATE(U67,"+") -> 65+ | J67: =IF(V67>1000,_xlfn.CONCAT(TEXT(V67/1000,"$#.0"),"T"),_xlfn.CONCAT(TEXT(V67,"$#"),"B")) -> $40B | K67: =_xlfn.CONCAT(TEXT(SUMIFS(raw_output!$N$2:$N$197,raw_output!$M$2:$M$197,'Overall Output. Labeled'!$N67,raw_output!$A$2:$A$197,'Overall Output. Labeled'!$U67,raw_output!$B$2:$B$197,'Overall Output. Labeled'!$S67,raw_output!$C$2:$C$197,'Overall Output. Labeled'!$T67,raw_output!$D$2:$D$197,'Overall Output. Labeled'!$P67,raw_output!$E$2:$E$197,'Overall Output. Labeled'!$Q67,raw_output!$F$2:$F$197,'Overall Output. Labeled'!$R67),"$#.0"),"T") -> $1.5T | L67: =IF(W67>1000,_xlfn.CONCAT(TEXT(W67/1000,"#.#"),"M"),_xlfn.CONCAT(TEXT(W67,"#"),"k")) -> 275k | M67: =TEXT(SUMIFS(raw_output!$L$2:$L$197,raw_output!$M$2:$M$197,'Overall Output. Labeled'!$N67,raw_output!$A$2:$A$197,'Overall Output. Labeled'!$U67,raw_output!$B$2:$B$197,'Overall Output. Labeled'!$S67,raw_output!$C$2:$C$197,'Overall Output. Labeled'!$T67,raw_output!$D$2:$D$197,'Overall Output. Labeled'!$P67,raw_output!$E$2:$E$197,'Overall Output. Labeled'!$Q67,raw_output!$F$2:$F$197,'Overall Output. Labeled'!$R67),"$#.##") -> -$19.85 | N67: 0.03 | O67: 0.11 | P67: 0.09 | Q67: 0.08 | R67: =H67*$O67 -> 0 | S67: 5 | T67: 10 | U67: 65 | V67: =SUMIFS(raw_output!$K$2:$K$197,raw_output!$M$2:$M$197,'Overall Output. Labeled'!$N67,raw_output!$A$2:$A$197,'Overall Output. Labeled'!$U67,raw_output!$B$2:$B$197,'Overall Output. Labeled'!$S67,raw_output!$C$2:$C$197,'Overall Output. Labeled'!$T67,raw_output!$D$2:$D$197,'Overall Output. Labeled'!$P67,raw_output!$E$2:$E$197,'Overall Output. Labeled'!$Q67,raw_output!$F$2:$F$197,'Overall Output. Labeled'!$R67) -> 40.442704 | W67: {=SUMIFS(raw_output!$J$2:$J$197,raw_output!$M$2:$M$197,'Overall Output. Labeled'!$N67,raw_output!$A$2:$A$197,'Overall Output. Labeled'!$U67,raw_output!$B$2:$B$197,'Overall Output. Labeled'!$S67,raw_output!$C$2:$C$197,'Overall Output. Labeled'!$T67,raw_output!$D$2:$D$197,'Overall Output. Labeled'!$P67,raw_output!$E$2:$E$197,'Overall Output. Labeled'!$Q67,raw_output!$F$2:$F$197,'Overall Output. Labeled'!$R67)*1000} -> 275.20844
A68: Nature Aging, Online Methods | C68: 1st gen, 4% | F68: 0.82 | G68: 0.727 | H68: 0 | I68: =CONCATENATE(U68,"+") -> 65+ | J68: =IF(V68>1000,_xlfn.CONCAT(TEXT(V68/1000,"$#.0"),"T"),_xlfn.CONCAT(TEXT(V68,"$#"),"B")) -> $40B | K68: =_xlfn.CONCAT(TEXT(SUMIFS(raw_output!$N$2:$N$197,raw_output!$M$2:$M$197,'Overall Output. Labeled'!$N68,raw_output!$A$2:$A$197,'Overall Output. Labeled'!$U68,raw_output!$B$2:$B$197,'Overall Output. Labeled'!$S68,raw_output!$C$2:$C$197,'Overall Output. Labeled'!$T68,raw_output!$D$2:$D$197,'Overall Output. Labeled'!$P68,raw_output!$E$2:$E$197,'Overall Output. Labeled'!$Q68,raw_output!$F$2:$F$197,'Overall Output. Labeled'!$R68),"$#.0"),"T") -> $.9T | L68: =IF(W68>1000,_xlfn.CONCAT(TEXT(W68/1000,"#.#"),"M"),_xlfn.CONCAT(TEXT(W68,"#"),"k")) -> 275k | M68: =TEXT(SUMIFS(raw_output!$L$2:$L$197,raw_output!$M$2:$M$197,'Overall Output. Labeled'!$N68,raw_output!$A$2:$A$197,'Overall Output. Labeled'!$U68,raw_output!$B$2:$B$197,'Overall Output. Labeled'!$S68,raw_output!$C$2:$C$197,'Overall Output. Labeled'!$T68,raw_output!$D$2:$D$197,'Overall Output. Labeled'!$P68,raw_output!$E$2:$E$197,'Overall Output. Labeled'!$Q68,raw_output!$F$2:$F$197,'Overall Output. Labeled'!$R68),"$#.##") -> -$19.85 | N68: 0.04 | O68: 0.11 | P68: 0.09 | Q68: 0.08 | R68: =H68*$O68 -> 0 | S68: 5 | T68: 10 | U68: 65 | V68: =SUMIFS(raw_output!$K$2:$K$197,raw_output!$M$2:$M$197,'Overall Output. Labeled'!$N68,raw_output!$A$2:$A$197,'Overall Output. Labeled'!$U68,raw_output!$B$2:$B$197,'Overall Output. Labeled'!$S68,raw_output!$C$2:$C$197,'Overall Output. Labeled'!$T68,raw_output!$D$2:$D$197,'Overall Output. Labeled'!$P68,raw_output!$E$2:$E$197,'Overall Output. Labeled'!$Q68,raw_output!$F$2:$F$197,'Overall Output. Labeled'!$R68) -> 40.442704 | W68: {=SUMIFS(raw_output!$J$2:$J$197,raw_output!$M$2:$M$197,'Overall Output. Labeled'!$N68,raw_output!$A$2:$A$197,'Overall Output. Labeled'!$U68,raw_output!$B$2:$B$197,'Overall Output. Labeled'!$S68,raw_output!$C$2:$C$197,'Overall Output. Labeled'!$T68,raw_output!$D$2:$D$197,'Overall Output. Labeled'!$P68,raw_output!$E$2:$E$197,'Overall Output. Labeled'!$Q68,raw_output!$F$2:$F$197,'Overall Output. Labeled'!$R68)*1000} -> 275.20844

Sheet Chapter 5 Tables
A1: Future 1: Slowing Brain Aging
A2: Mortality decrease in years | B2: Productivity increase in years | C2: Fertility increase in years | D2: Ages Affected | E2: Average change in US GDP over first 20 years | F2: NPV of increased GDP over several decades | G2: Lives saved or gained
A3: ='Overall Output. Labeled'!F3 -> 0.2 | B3: ='Overall Output. Labeled'!G3 -> 0.7 | C3: ='Overall Output. Labeled'!H3 -> 0 | D3: ='Overall Output. Labeled'!I3 -> 40+ | E3: ='Overall Output. Labeled'!J3 -> $201B | F3: ='Overall Output. Labeled'!K3 -> $8.9T | G3: ='Overall Output. Labeled'!L3 -> 268k
A4: Notes: Results from simulation using the OG-USA model. Simulation assumes a 50% adherence rate to new medical interventions. NPV computed using a discount rate of 2%. See appendix for more modeling details

Sheet Chapter 6 Tables
A1: Future 2: Slowing Reproductive Aging
A2: Mortality decrease in years | B2: Productivity increase in years | C2: Fertility increase in years | D2: Ages Affected | E2: Average change in US GDP over first 20 years | F2: NPV of increased GDP over several decades | G2: Lives saved or gained
A3: ='Overall Output. Labeled'!F4 -> 0.02 | B3: ='Overall Output. Labeled'!G4 -> 0.1 | C3: ='Overall Output. Labeled'!H4 -> 1 | D3: ='Overall Output. Labeled'!I4 -> 40+ | E3: ='Overall Output. Labeled'!J4 -> $9B | F3: ='Overall Output. Labeled'!K4 -> $9.3T | G3: ='Overall Output. Labeled'!L4 -> 391k
A4: Notes: Results from simulation using the OG-USA model. Simulation assumes a 50% adherence rate to new medical interventions and adjusts for women's fertility choices. NPV computed using a discount rate of 2%. See appendix for more modeling details.

Sheet Chapter 7 Tables
A1: Future 3: Replacing Aging
B2: Mortality decrease in years | C2: Productivity increase in years | D2: Fertility increase in years | E2: Average change in US GDP over first 20 years | F2: NPV of increased GDP over several decades | G2: Lives saved or gained
A3: 2x Organ Supply | B3: ='Overall Output. Labeled'!F6 -> 0.22 | C3: ='Overall Output. Labeled'!G6 -> 0 | D3: ='Overall Output. Labeled'!H6 -> 0 | E3: ='Overall Output. Labeled'!J6 -> $50B | F3: ='Overall Output. Labeled'!K6 -> $3.2T | G3: ='Overall Output. Labeled'!L6 -> 592k
A4: 4x Organ Supply | B4: ='Overall Output. Labeled'!F5 -> 0.44 | C4: ='Overall Output. Labeled'!G5 -> 0 | D4: ='Overall Output. Labeled'!H5 -> 0 | E4: ='Overall Output. Labeled'!J5 -> $118B | F4: ='Overall Output. Labeled'!K5 -> $6.8T | G4: ='Overall Output. Labeled'!L5 -> 1.2M
A5: Notes: Results from simulation using the OG-USA model. Simulation assumes a four-fold increase in organ transplantation. NPV computed using a discount rate of 2%. See appendix for more modeling details.

Sheet Chapter 8 Tables
A1: Future 4: Marginally Slowing Aging
A2: Treatment | B2: Population Affected | C2: Average change in US GDP over first 20 years | D2: NPV of increased GDP over several decades | E2: Lives saved or gained
A3: 1st Gen (TAME trial) Cost: $55 million Effects start: 2030 Full Market Entry: 2035 | B3: 65+ (1 disease of aging/slow gait speed - 11% of non-diabetic older adults) | C3: ='Overall Output. Labeled'!J7 -> $40B | D3: ='Overall Output. Labeled'!K7 -> $2.4T | E3: ='Overall Output. Labeled'!L7 -> 275k
B4: 65+ (50% of all non-diabetic older adults) | C4: ='Overall Output. Labeled'!J8 -> $79B | D4: ='Overall Output. Labeled'!K8 -> $4.2T | E4: ='Overall Output. Labeled'!L8 -> 460k
A5: Notes: Results from simulations using the OG-USA model. NPV computed using a discount rate of 2%. See appendix for more modeling details.
A11: Future 4: From 1st Gen to 2nd Gen Treatments
A12: Treatment | B12: Population Affected | C12: Average change in US GDP over first 20 years | D12: NPV of increased GDP over several decades | E12: Lives saved or gained
A13: 1st Gen (TAME trial, existing drug) Cost: $55 million | B13: 65+ (1 disease of aging/slow gait speed - 11% of non-diabetic older adults) - TREATMENT + collect & validate biomarkets | C13: =C3 -> $40B | D13: =D3 -> $2.4T | E13: =E3 -> 275k
A14: 2nd Gen (Counterfactual therapeutic) Cost: Unknown | B14: 40+ (mostly healthy, decent lifestyle - 50% of the population 40+ is eligible) - PREVENTION | C14: ='Overall Output. Labeled'!J9 -> $505B | D14: ='Overall Output. Labeled'!K9 -> $22.2T | E14: ='Overall Output. Labeled'!L9 -> 1.1M
A15: Delta | B15: 2nd gen - 1st gen | C15: ='Overall Output. Labeled'!J10 -> $426B | D15: ='Overall Output. Labeled'!K10 -> $36.2T | E15: ='Overall Output. Labeled'!L10 -> 650k
A16: Notes: Results from simulations using the OG-USA model. NPV computed using a discount rate of 2%. See appendix for more modeling details.
A22: Future 4: Development with Human-Relevant Methodologies
A23: Treatment | B23: Population Affected | C23: Average change in US GDP over first 20 years | D23: NPV of increased GDP over several decades | E23: Lives saved or gained
A24: 2nd Gen (Counterfactual therapeutic) | B24: 40+ (mostly healthy, decent lifestyle)) - PREVENTION | C24: =C14 -> $505B | D24: =D14 -> $22.2T | E24: =E14 -> 1.1M
A25: 2nd Gen + human relevant methodologies (e.g., virtual cells, organs on chips) | B25: 40+ (mostly healthy, decent lifestyle) - PREVENTION + 20% development speed | C25: ='Overall Output. Labeled'!J11 -> $523B | D25: ='Overall Output. Labeled'!K11 -> $23.3T | E25: ='Overall Output. Labeled'!L11 -> 1.3M
A26: Delta | B26: 2nd gen+ - 2nd gen | C26: ='Overall Output. Labeled'!J12 -> $18B | D26: ='Overall Output. Labeled'!K12 -> $2.0T | E26: ='Overall Output. Labeled'!L12 -> 221k
A27: Notes: Results from simulations using the OG-USA model. NPV computed using a discount rate of 2%. See appendix for more modeling details.

Sheet Chapter 9 Tables
A1: Future 5: Making 41 the new 40
A2: Mortality decrease in years | B2: Productivity increase in years | C2: Fertility increase in years | D2: Ages Affected | E2: Average change in US GDP over first 20 years | F2: NPV of increased GDP over several decades | G2: Lives saved or gained
A3: ='Overall Output. Labeled'!F13 -> 1 | B3: ='Overall Output. Labeled'!G13 -> 1 | C3: ='Overall Output. Labeled'!H13 -> 1 | D3: ='Overall Output. Labeled'!I13 -> 40+ | E3: ='Overall Output. Labeled'!J13 -> $408B | F3: ='Overall Output. Labeled'!K13 -> $27.1T | G3: ='Overall Output. Labeled'!L13 -> 1.7M
A4: Notes: Results from simulation using the OG-USA model. Simulation assumes a 50% adherence rate to new medical interventions. NPV computed using a discount rate of 2%. See appendix for more modeling details
A10: Future 5: Slowing Aging by 1 and 5 Years
A11: Mortality decrease in years | B11: Productivity increase in years | C11: Fertility increase in years | D11: Ages Affected | E11: Average change in US GDP over first 20 years | F11: NPV of increased GDP over several decades | G11: Lives saved or gained
A12: ='Overall Output. Labeled'!F13 -> 1 | B12: ='Overall Output. Labeled'!G13 -> 1 | C12: ='Overall Output. Labeled'!H13 -> 1 | D12: ='Overall Output. Labeled'!I13 -> 40+ | E12: ='Overall Output. Labeled'!J13 -> $408B | F12: ='Overall Output. Labeled'!K13 -> $27.1T | G12: ='Overall Output. Labeled'!L13 -> 1.7M
A13: ='Overall Output. Labeled'!F14 -> 1 | B13: ='Overall Output. Labeled'!G14 -> 1 | C13: ='Overall Output. Labeled'!H14 -> 1 | D13: ='Overall Output. Labeled'!I14 -> 65+ | E13: ='Overall Output. Labeled'!J14 -> $326B | F13: ='Overall Output. Labeled'!K14 -> $14.3T | G13: ='Overall Output. Labeled'!L14 -> 1.2M
A14: ='Overall Output. Labeled'!F15 -> 5 | B14: ='Overall Output. Labeled'!G15 -> 5 | C14: ='Overall Output. Labeled'!H15 -> 5 | D14: ='Overall Output. Labeled'!I15 -> 40+ | E14: ='Overall Output. Labeled'!J15 -> $2.0T | F14: ='Overall Output. Labeled'!K15 -> $101.9T | G14: ='Overall Output. Labeled'!L15 -> 6.9M
A15: ='Overall Output. Labeled'!F16 -> 5 | B15: ='Overall Output. Labeled'!G16 -> 5 | C15: ='Overall Output. Labeled'!H16 -> 5 | D15: ='Overall Output. Labeled'!I16 -> 65+ | E15: ='Overall Output. Labeled'!J16 -> $1.7T | F15: ='Overall Output. Labeled'!K16 -> $72.8T | G15: ='Overall Output. Labeled'!L16 -> 5.6M
A16: Notes: Results from simulations using the OG-USA model. Simulation assumes a 50% adherence rate to new medical interventions. NPV computed using a discount rate of 2%. See appendix for more modeling details

Sheet Chapter 11 Tables
A1: A comparison between two ambitious goals: eliminating all cancers, or shifting biological age back by 5 years.
A2: Breakthrough | B2: Patient Adherence | C2: NPV of increased GDP over several decades | D2: Discount Rate
A3: Curing all cancers | B3: 1 | C3: ='Overall Output. Labeled'!K17 -> $80T | D3: ='Overall Output. Labeled'!N17 -> 0.035
A4: Shifting biological age back by 5 years | B4: 1 | C4: ='Overall Output. Labeled'!K18 -> $83.6T | D4: ='Overall Output. Labeled'!N18 -> 0.035
A5: Notes: Results from simulation using the OG-USA model. See appendix for more modeling details.
A11: Comparison to Other Investments
A12: Breakthrough | B12: Patient Adherence | C12: NPV of increased GDP over several decades | D12: Effect ceiling
A13: Deploying existing malaria vaccines | B13: 1 | C13: ='Overall Output. Labeled'!K19 -> $36.0T | D13: ~100% of malaria incidence eliminated
A14: Regular exercise | B14: 1 | C14: ='Overall Output. Labeled'!K20 -> $38.4T | D14: ~100% of the US population. Effecsts have diminishing returns.
A15: Notes: Malaria results come from the authors' extrapolation of Oxford Economics (2024). Malaria affects about 1% of the global population. Exercise results are from a simulation using the OG-USA model, assuming exercise increases lifespan by 2.3 years (as in Reimers et al. (2012)). See appendix for more modeling details.

Sheet Chapter 12 Tables
A1: Making 41 the New 40: A Comparison of Alternative Methodologies
A2: Methodology | B2: Average change in US GDP over first 20 years | C2: NPV of increased GDP over several decades | D2: Discount Rate
A3: Total Product | B3: ='Overall Output. Labeled'!J21 -> $857B | C3: ='Overall Output. Labeled'!K21 -> $47.1T | D3: ='Overall Output. Labeled'!N21 -> 0.02
A4: Theoretical VSL ($14.3M/statistical life) | B4: N/A* | C4: ='Overall Output. Labeled'!K22 -> $46.8T | D4: ='Overall Output. Labeled'!N22 -> 0.02
A5: QALY ($160k/QALY) | B5: ='Overall Output. Labeled'!J23 -> $857B | C5: ='Overall Output. Labeled'!K23 -> $28.4T | D5: ='Overall Output. Labeled'!N23 -> 0.02
A6: Notes: Total product and QALY results come from the OG-USA model, assuming 100% adherence to the treatment. The $160,000 QALY represents an inflation-adjusted value for the QALY estimate used in Cutler (2004), putting the value in 2025 dollars. Theoretical VSL values are from Scott et al. (2021), adjusted for inflation to put in 2025 dollars. *Scott et al. (2021) methods do not allow for a decomposition of annual effects.
A15: Counterfactual Futures: Effects on GDP per Capita
A16: Future | B16: NPV of increased GDP over several decades | C16: Increase in GDP per capita over first 20 years
A17: 1st -generation therapeutics | B17: ='Overall Output. Labeled'!K7 -> $2.4T | C17: ='Overall Output. Labeled'!M7 -> -$19.85
A18: Slow brain aging by one year | B18: ='Overall Output. Labeled'!K3 -> $8.9T | C18: ='Overall Output. Labeled'!M3 -> $507.82
A19: Slow reproductive aging by one year | B19: ='Overall Output. Labeled'!K4 -> $9.3T | C19: ='Overall Output. Labeled'!M4 -> -$5.25
A20: "Replace" aging (4x increase in organ abundance) | B20: ='Overall Output. Labeled'!K5 -> $6.8T | C20: ='Overall Output. Labeled'!M5 -> -$436.88
A21: Slow overall biological aging by one year | B21: ='Overall Output. Labeled'!K13 -> $27.1T | C21: ='Overall Output. Labeled'!M13 -> $425.39
A22: Notes: Results from OG-USA simulations. Simulations other than the 1st-generation therapeutics assume a 50% adherence rate among those aged 40+. The 1st-generation therapeutics simulation assumes treatment of 11% of those aged 65+.

Sheet Appendix Tables
A1: Decomposition of a 1-year Shift in Biological Aging
A2: Mortality decrease in years | B2: Productivity increase in years | C2: Fertility increase in years | D2: Average change in US GDP over first 20 years | E2: NPV of increased GDP over several decades | F2: Lives saved or gained
A3: 1 | B3: 0 | C3: 0 | D3: ='Overall Output. Labeled'!J24 -> $137B | E3: ='Overall Output. Labeled'!K24 -> $7.8T | F3: ='Overall Output. Labeled'!L24 -> 1.4M
A4: 0 | B4: 1 | C4: 0 | D4: ='Overall Output. Labeled'!J25 -> $252B | E4: ='Overall Output. Labeled'!K25 -> $10.6T | F4: 0k
A5: 0 | B5: 0 | C5: 1 | D5: ='Overall Output. Labeled'!J26 -> -$21B | E5: ='Overall Output. Labeled'!K26 -> $8.0T | F5: 0k
A6: 1 | B6: 1 | C6: 1 | D6: ='Overall Output. Labeled'!J13 -> $408B | E6: ='Overall Output. Labeled'!K13 -> $27.1T | F6: ='Overall Output. Labeled'!L13 -> 1.7M
A7: Notes: Results from simulations using the OG-USA model. Simulation assumes a 50% adherence rate to new medical interventions, and effects on those aged 40+. NPV computed using a discount rate of 2%.
A13: Equal Percentage Changes in Each Channel
A14: Mortality decrease | B14: Productivity increase | C14: Fertility increase | D14: Average change in US GDP over first 20 years | E14: NPV of increased GDP over several decades | F14: Lives saved or gained
A15: 0.01 | B15: 0 | C15: 0 | D15: ='Overall Output. Labeled'!J27 -> $22B | E15: ='Overall Output. Labeled'!K27 -> $1.8T | F15: ='Overall Output. Labeled'!L27 -> 349k
A16: 0 | B16: 0.01 | C16: 0 | D16: ='Overall Output. Labeled'!J28 -> $236B | E16: ='Overall Output. Labeled'!K28 -> $9.9T | F16: 0k
A17: 0 | B17: 0 | C17: 0.01 | D17: ='Overall Output. Labeled'!J29 -> -$21B | E17: ='Overall Output. Labeled'!K29 -> $8.7T | F17: 0k
A18: 0.01 | B18: 0.01 | C18: 0.01 | D18: ='Overall Output. Labeled'!J30 -> $274B | E18: ='Overall Output. Labeled'!K30 -> $21.0T | F18: ='Overall Output. Labeled'!L30 -> 743k
A19: Notes: Results from simulations using the OG-USA model. Simulations assume effects on those aged 40+. NPV computed using a discount rate of 2%.
A25: Sensitivity to Discount Rates: 41 is the New 40 | I25: Nature Aging: Sensitivity to Discount Rates in NPV Calculations
A26: Discount Rate | B26: NPV of increased GDP over several decades | I26: Discount Rate | J26: Slowing brain aging by 1 year | K26: Slowing reproductive aging by 1 year | L26: Slowing overall aging by 1 year for all adults age 40+ | M26: Slowing overall aging by 1 year for all adults age 65+ | N26: TAME, 1st Gen
A27: 0.01 | B27: ='Overall Output. Labeled'!K31 -> $53.3T | I27: 0.01 | J27: ='Overall Output. Labeled'!K53 -> $16.1T | K27: ='Overall Output. Labeled'!K57 -> $19.5T | L27: ='Overall Output. Labeled'!K49 -> $53.3T | M27: ='Overall Output. Labeled'!K61 -> $26.0T | N27: ='Overall Output. Labeled'!K65 -> $4.3T
A28: 0.02 | B28: ='Overall Output. Labeled'!K13 -> $27.1T | I28: 0.02 | J28: ='Overall Output. Labeled'!K54 -> $8.9T | K28: ='Overall Output. Labeled'!K58 -> $8.6T | L28: ='Overall Output. Labeled'!K50 -> $27.1T | M28: ='Overall Output. Labeled'!K62 -> $14.3T | N28: ='Overall Output. Labeled'!K66 -> $2.4T
A29: 0.03 | B29: ='Overall Output. Labeled'!K32 -> $14.6T | I29: 0.03 | J29: ='Overall Output. Labeled'!K55 -> $5.2T | K29: ='Overall Output. Labeled'!K59 -> $3.9T | L29: ='Overall Output. Labeled'!K51 -> $14.6T | M29: ='Overall Output. Labeled'!K63 -> $8.4T | N29: ='Overall Output. Labeled'!K67 -> $1.5T
A30: 0.04 | B30: ='Overall Output. Labeled'!K33 -> $8.3T | I30: 0.04 | J30: ='Overall Output. Labeled'!K56 -> $3.2T | K30: ='Overall Output. Labeled'!K60 -> $1.8T | L30: ='Overall Output. Labeled'!K52 -> $8.3T | M30: ='Overall Output. Labeled'!K64 -> $5.2T | N30: ='Overall Output. Labeled'!K68 -> $.9T
A31: 0.05 | B31: ='Overall Output. Labeled'!K34 -> $5.0T | I31: Notes: Results from simulations using the OG-USA model. Simulation assumes a 50% adherence rate to new medical interventions, and effects on those aged 40+, except for TAME Trial. See appendix for more modeling details
A32: Notes: Results from simulations using the OG-USA model. Simulation assumes a 50% adherence rate to new medical interventions, and effects on those aged 40+. See appendix for more modeling details
I42: Discount Rate | J42: Slowing brain aging by 1 year | K42: Slowing reproductive aging by 1 year | L42: Slowing overall aging by 1 year for all adults age 40+ | M42: Slowing overall aging by 1 year for all adults age 65+ | N42: TAME, 1st Gen
I43: 0.01 | J43: 16.5 | K43: 19.1 | L43: 42.5 | M43: 26.8 | N43: 4.7
I44: 0.02 | J44: 9.1 | K44: 8.5 | L44: 22.5 | M44: 14.8 | N44: 2.7
I45: 0.03 | J45: 5.4 | K45: 3.9 | L45: 12.6 | M45: 8.6 | N45: 1.7
I46: 0.04 | J46: 3.3 | K46: 1.8 | L46: 7.4 | M46: 5.3 | N46: 1.1
